Workbook
Name \A: #REF!
Name \B: #REF!
Name \C: #REF!
Name \D: #REF!
Name \E: #REF!
Name \F: #REF!
Name \G: #REF!
Name \H: #REF!
Name \I: #REF!
Name \J: #REF!
Name \K: #REF!
Name \L: #REF!
Name \M: #REF!
Name \N: #REF!
Name \O: #REF!
Name \P: #REF!
Name \Q: #REF!
Name \R: #REF!
Name \S: #REF!
Name \T: #REF!
Name \U: #REF!
Name \V: #REF!
Name \W: #REF!
Name \X: #REF!
Name \Y: #REF!
Name \Z: #REF!
Name ___BOP2: [1]BoP!#REF!
Name ___EXP5: #REF!
Name ___EXP6: #REF!
Name ___EXP7: #REF!
Name ___EXP9: #REF!
Name ___IMP2: #REF!
Name ___IMP4: #REF!
Name ___IMP6: #REF!
Name ___IMP7: #REF!
Name ___MTS2: '[2]Annual Tables'!#REF!
Name ___PAG2: [2]Index!#REF!
Name ___PAG3: [2]Index!#REF!
Name ___PAG4: [2]Index!#REF!
Name ___PAG5: [2]Index!#REF!
Name ___PAG6: [2]Index!#REF!
Name ___RES2: [1]RES!#REF!
Name ___TAB7: #REF!
Name __BOP1: #REF!
Name __IMP10: #REF!
Name __IMP8: #REF!
Name __PAG7: #REF!
Name __TAB1: #REF!
Name __TAB10: #REF!
Name __TAB12: #REF!
Name __Tab19: #REF!
Name __TAB2: #REF!
Name __Tab20: #REF!
Name __Tab21: #REF!
Name __Tab22: #REF!
Name __Tab23: #REF!
Name __Tab24: #REF!
Name __Tab26: #REF!
Name __Tab27: #REF!
Name __Tab28: #REF!

Sheet 1.Reel GSYH 
B1: Ülke Analizi
B2: Toplam Talep Analizi
B3: Reel GSYH Bileşenleri
B6: =D9+K9+M9+U9+Y9 | D6: =SUM(E9:I9) | M6: =N9+Q9 | Q6: =R9+S9 | Y6: =W9-X9
D7: Özel Tüketim Harcamaları Bileşenleri | K7: Kamu Reel Nihai Tüketim Harcamalarının Bileşenleri | M7: Brüt Sabit Sermaye Oluşumu (Gross Fixed Capital Formation) | N7: Reel Kamu Bileşenleri Brüt Sabit Sermaye Oluşumu | Q7: Reel Özel Bileşenleri Brüt Sabit Sermaye Oluşumu | U7: Stok Değişimi | W7: Net İhracat: Mal ve Hizmet Ticareti
B8: Reel GSYH (Düzey, 2008 Fiyatları-DND Milyar) | D8: Toplam Özel Tüketim (Cp) TL milyon | E8: Dayanıklı Tüketim TL milyon | F8: Yarı-Dayanıklı Tüketim TL milyon | G8: Dayanıklı Olmayan Tüketim TL milyon | H8: Hizmetler TL milyon | I8: Diğerleri, Mevsimsellikten arındırılmış TL milyon | K8: Toplam Kamu Tüketim (Cg) TL milyon | M8: Toplam Özel ve Kamu GFCF tl milyon | N8: Toplam Kamu GFCF (Ig) (Düzey, 2008 Fiyatları-DND Milyar) | O8: Kamu Makina & Ekipman (Düzey, 2008 Fiyatları-DND Milyar) | P8: Kamu İnşaat (Düzey, 2008 Fiyatları-DND Milyar) | Q8: Toplam Özel GFCF (Ip) (Düzey, 2008 Fiyatları-DND Milyar) | R8: Özel Makina & Ekipman (Düzey, 2008 Fiyatları-DND Milyar) | S8: Özel İnşaat (Düzey, 2008 Fiyatları-DND Milyar) | U8: Stok Değişimi (Düzey, 2008 Fiyatları-DND Milyar) | W8: Mal ihracatı ve Hizmetler (X) (Düzey, 2008 Fiyatları-DND Milyar) | X8: Mal ithalatı ve Hizmetler (IM) (Düzey, 2008 Fiyatları-DND Milyar) | Y8: Net İhracat (NX) (Düzey, 2008 Fiyatları-DND Milyar)
A9: Q1-1993 | U9: 23.293625 | Y9: =W9-X9 -> 0
A10: Q2-1993 | U10: 29.357175 | Y10: =W10-X10 -> 0
A11: Q3-1993 | U11: 18.210875 | Y11: =W11-X11 -> 0
A12: Q4-1993 | U12: 9.5901 | Y12: =W12-X12 -> 0
A13: Q1-1994 | U13: 15.654625 | Y13: =W13-X13 -> 0
A14: Q2-1994 | U14: 39.951925 | Y14: =W14-X14 -> 0
A15: Q3-1994 | U15: 19.97175 | Y15: =W15-X15 -> 0
A16: Q4-1994 | U16: 24.088725 | Y16: =W16-X16 -> 0
A17: Q1-1995 | U17: 26.944575 | Y17: =W17-X17 -> 0
A18: Q2-1995 | U18: 26.403175 | Y18: =W18-X18 -> 0
A19: Q3-1995 | U19: 35.6198 | Y19: =W19-X19 -> 0
A20: Q4-1995 | U20: 41.673575 | Y20: =W20-X20 -> 0
... A28: Q4-1997 | U28: 36.000075 | Y28: =W28-X28 -> 0
A29: Q1-1998 | K29: 1555721747 | W29: 3178269942 | X29: 3375501685 | Y29: =W29-X29 -> -197231743
A30: Q2-1998 | K30: 1749982774 | W30: 3570590925 | X30: 3494121398 | Y30: =W30-X30 -> 76469527
A31: Q3-1998 | K31: 2.0128767e+09 | W31: 3869069892 | X31: 3564655645 | Y31: =W31-X31 -> 304414247
A32: Q4-1998 | K32: 2317070339 | W32: 4.2503263e+09 | X32: 3759821120 | Y32: =W32-X32 -> 4.9050514e+08
A33: Q1-1999 | K33: 2870410633 | W33: 4445471150 | X33: 3863263372 | Y33: =W33-X33 -> 582207778
A34: Q2-1999 | K34: 3059143782 | W34: 4627148670 | X34: 4840368749 | Y34: =W34-X34 -> -213220079
A35: Q3-1999 | K35: 3671287486 | W35: 5025310424 | X35: 5078603827 | Y35: =W35-X35 -> -53293403
A36: Q4-1999 | K36: 4001932718 | W36: 6100147498 | X36: 6462116836 | Y36: =W36-X36 -> -361969338
A37: Q1-2000 | K37: 4459007547 | W37: 7381271101 | X37: 8655351781 | Y37: =W37-X37 -> -1274080680
A38: Q2-2000 | K38: 4955868912 | W38: 8.4274077e+09 | X38: 9499986401 | Y38: =W38-X38 -> -1.0725787e+09
A39: Q3-2000 | K39: 5358721868 | W39: 8862633102 | X39: 9720140787 | Y39: =W39-X39 -> -857507685
A40: Q4-2000 | K40: 5683358116 | W40: 9423793094 | X40: 10664823250 | Y40: =W40-X40 -> -1241030156
... A72: Q4-2008 | K72: 34531531990 | W72: 58373358520 | X72: 60996060010 | Y72: =W72-X72 -> -2622701490
A73: Q1-2009 | B73: =D73+K73+M73+U73+Y73 -> 4.1711555e+10 | D73: =SUM(E73:I73) -> 273435.7 | E73: 9472.3 | F73: 15446.1 | G73: 46185.9 | H73: 72183.6 | I73: 130147.8 | K73: 37205453390 | W73: 59129027450 | X73: 54623199750 | Y73: =W73-X73 -> 4505827700
A74: Q2-2009 | B74: =D74+K74+M74+U74+Y74 -> 3.7452284e+10 | D74: =SUM(E74:I74) -> 303049.9 | E74: 13867.4 | F74: 14821.1 | G74: 54581.3 | H74: 75667.6 | I74: 144112.5 | K74: 38245187990 | W74: 54508058600 | X74: 55301265380 | Y74: =W74-X74 -> -793206780
A75: Q3-2009 | B75: =D75+K75+M75+U75+Y75 -> 3.8455469e+10 | D75: =SUM(E75:I75) -> 340495.8 | E75: 13070.6 | F75: 16667.7 | G75: 68853.6 | H75: 78027.4 | I75: 163876.5 | K75: 39645740940 | W75: 60595791840 | X75: 61786404020 | Y75: =W75-X75 -> -1190612180
A76: Q4-2009 | B76: =D76+K76+M76+U76+Y76 -> 3.9488665e+10 | D76: =SUM(E76:I76) -> 328447.9 | E76: 13576.9 | F76: 17942.9 | G76: 57638.6 | H76: 79705.3 | I76: 159584.2 | K76: 42480006080 | W76: 60958375210 | X76: 63950044460 | Y76: =W76-X76 -> -2991669250
A77: Q1-2010 | B77: =D77+K77+M77+U77+Y77 -> 3.3797608e+10 | D77: =SUM(E77:I77) -> 300063.7 | E77: 12003.8 | F77: 16858.8 | G77: 48168.8 | H77: 75229.9 | I77: 147802.4 | K77: 41401830940 | W77: 57456631490 | X77: 6.5061155e+10 | Y77: =W77-X77 -> -7.6045231e+09
A78: Q2-2010 | B78: =D78+K78+M78+U78+Y78 -> 3.3818168e+10 | D78: =SUM(E78:I78) -> 338610.7 | E78: 14470.4 | F78: 19772.9 | G78: 57817.9 | H78: 79709.3 | I78: 166840.2 | K78: 42627117410 | W78: 63261992640 | X78: 72071281130 | Y78: =W78-X78 -> -8809288490
A79: Q3-2010 | B79: =D79+K79+M79+U79+Y79 -> 2.9346809e+10 | D79: =SUM(E79:I79) -> 394172.1 | E79: 14482.6 | F79: 20155.3 | G79: 79079.9 | H79: 85003.1 | I79: 195451.2 | K79: 44421898300 | W79: 61734911860 | X79: 76810395110 | Y79: =W79-X79 -> -15075483250
A80: Q4-2010 | B80: =D80+K80+M80+U80+Y80 -> 2.6441801e+10 | D80: =SUM(E80:I80) -> 375040.8 | E80: 18909.4 | F80: 20018.2 | G80: 62600.9 | H80: 87438.4 | I80: 186073.9 | K80: 45234082450 | W80: 65022830400 | X80: 83815486970 | Y80: =W80-X80 -> -18792656570
A81: Q1-2011 | B81: =D81+K81+M81+U81+Y81 -> 2.0502316e+10 | D81: =SUM(E81:I81) -> 359659.9 | E81: 16529.5 | F81: 23137.9 | G81: 55977.4 | H81: 84085.8 | I81: 179929.3 | K81: 46074748340 | W81: 71985086070 | X81: 97557878410 | Y81: =W81-X81 -> -25572792340
A82: Q2-2011 | B82: =D82+K82+M82+U82+Y82 -> 1.9288986e+10 | D82: =SUM(E82:I82) -> 399958.6 | E82: 19098.9 | F82: 23366.5 | G82: 65328.2 | H82: 89968.1 | I82: 202196.9 | K82: 46973920890 | W82: 74966462240 | X82: 102651797300 | Y82: =W82-X82 -> -27685335060
A83: Q3-2011 | B83: =D83+K83+M83+U83+Y83 -> 20825080286 | D83: =SUM(E83:I83) -> 447356 | E83: 17801.8 | F83: 25012.9 | G83: 82795.9 | H83: 92516.8 | I83: 229228.6 | K83: 46996409100 | W83: 87437749730 | X83: 113609525900 | Y83: =W83-X83 -> -26171776170
A84: Q4-2011 | B84: =D84+K84+M84+U84+Y84 -> 27665035933 | D84: =SUM(E84:I84) -> 431313 | E84: 19788.6 | F84: 23775.3 | G84: 68534.6 | H84: 94658.7 | I84: 224555.8 | K84: 51030067210 | W84: 88655560610 | X84: 112021023200 | Y84: =W84-X84 -> -23365462590
... A103: Q3-2016 | B103: =D103+K103+M103+U103+Y103 -> 7.8800443e+10 | D103: =SUM(E103:I103) -> 633640.3 | E103: 23443 | F103: 25604.2 | G103: 90550.4 | H103: 114067 | I103: 379975.7 | K103: 93948421030 | W103: 139404494100 | X103: 154553105600 | Y103: =W103-X103 -> -15148611500
A109: Ortalamalar
A110: 1998-2001 | B110: =AVERAGE(B32:B47) -> #DIV/0! | D110: =AVERAGE(D32:D47) -> #DIV/0! | E110: =AVERAGE(E32:E47) -> #DIV/0! | F110: =AVERAGE(F32:F47) -> #DIV/0! | G110: =AVERAGE(G32:G47) -> #DIV/0! | H110: =AVERAGE(H32:H47) -> #DIV/0! | I110: =AVERAGE(I32:I47) -> #DIV/0! | K110: =AVERAGE(K32:K47) -> 6.3104028e+09 | M110: =AVERAGE(M32:M47) -> #DIV/0! | N110: =AVERAGE(N32:N47) -> #DIV/0! | O110: =AVERAGE(O32:O47) -> #DIV/0! | P110: =AVERAGE(P32:P47) -> #DIV/0! | Q110: =AVERAGE(Q32:Q47) -> #DIV/0! | R110: =AVERAGE(R32:R47) -> #DIV/0! | S110: =AVERAGE(S32:S47) -> #DIV/0! | U110: =AVERAGE(U32:U47) -> #DIV/0! | W110: =AVERAGE(W32:W47) -> 1.1916022e+10 | X110: =AVERAGE(X32:X47) -> 1.1063046e+10 | Y110: =AVERAGE(Y32:Y47) -> 8.5297606e+08
A111: 2002-2005 | B111: =AVERAGE(B48:B63) -> #DIV/0! | D111: =AVERAGE(D48:D63) -> #DIV/0! | E111: =AVERAGE(E48:E63) -> #DIV/0! | F111: =AVERAGE(F48:F63) -> #DIV/0! | G111: =AVERAGE(G48:G63) -> #DIV/0! | H111: =AVERAGE(H48:H63) -> #DIV/0! | I111: =AVERAGE(I48:I63) -> #DIV/0! | K111: =AVERAGE(K48:K63) -> 1.8943972e+10 | M111: =AVERAGE(M48:M63) -> #DIV/0! | N111: =AVERAGE(N48:N63) -> #DIV/0! | O111: =AVERAGE(O48:O63) -> #DIV/0! | P111: =AVERAGE(P48:P63) -> #DIV/0! | Q111: =AVERAGE(Q48:Q63) -> #DIV/0! | R111: =AVERAGE(R48:R63) -> #DIV/0! | S111: =AVERAGE(S48:S63) -> #DIV/0! | U111: =AVERAGE(U48:U63) -> #DIV/0! | W111: =AVERAGE(W48:W63) -> 3.4472037e+10 | X111: =AVERAGE(X48:X63) -> 3.7584074e+10 | Y111: =AVERAGE(Y48:Y63) -> -3.1120373e+09
A112: 2006-2009 | B112: =AVERAGE(B64:B79) -> 3.6295794e+10 | D112: =AVERAGE(D64:D79) -> 325467.97 | E112: =AVERAGE(E64:E79) -> 12992 | F112: =AVERAGE(F64:F79) -> 17380.686 | G112: =AVERAGE(G64:G79) -> 58903.714 | H112: =AVERAGE(H64:H79) -> 77932.314 | I112: =AVERAGE(I64:I79) -> 158259.26 | K112: =AVERAGE(K64:K79) -> 3.5507559e+10 | M112: =AVERAGE(M64:M79) -> #DIV/0! | N112: =AVERAGE(N64:N79) -> #DIV/0! | O112: =AVERAGE(O64:O79) -> #DIV/0! | P112: =AVERAGE(P64:P79) -> #DIV/0! | Q112: =AVERAGE(Q64:Q79) -> #DIV/0! | R112: =AVERAGE(R64:R79) -> #DIV/0! | S112: =AVERAGE(S64:S79) -> #DIV/0! | U112: =AVERAGE(U64:U79) -> #DIV/0! | W112: =AVERAGE(W64:W79) -> 5.6005114e+10 | X112: =AVERAGE(X64:X79) -> 6.282403e+10 | Y112: =AVERAGE(Y64:Y79) -> -6.8189153e+09
A113: 2010-2016 | B113: =AVERAGE(B80:B103) -> 4.9017454e+10 | D113: =AVERAGE(D80:D103) -> 496768.26 | E113: =AVERAGE(E80:E103) -> 22628.712 | F113: =AVERAGE(F80:F103) -> 24713.113 | G113: =AVERAGE(G80:G103) -> 72626 | H113: =AVERAGE(H80:H103) -> 102667.69 | I113: =AVERAGE(I80:I103) -> 274132.75 | K113: =AVERAGE(K80:K103) -> 6.7223263e+10 | M113: =AVERAGE(M80:M103) -> #DIV/0! | N113: =AVERAGE(N80:N103) -> #DIV/0! | O113: =AVERAGE(O80:O103) -> #DIV/0! | P113: =AVERAGE(P80:P103) -> #DIV/0! | Q113: =AVERAGE(Q80:Q103) -> #DIV/0! | R113: =AVERAGE(R80:R103) -> #DIV/0! | S113: =AVERAGE(S80:S103) -> #DIV/0! | U113: =AVERAGE(U80:U103) -> #DIV/0! | W113: =AVERAGE(W80:W103) -> 1.140541e+11 | X113: =AVERAGE(X80:X103) -> 1.322604e+11 | Y113: =AVERAGE(Y80:Y103) -> -1.8206306e+10

Sheet 1a. Reel GSYH Payı
B1: Ülke Analizi
B2: Toplam Talep Analizi
B3: GSYH unsurlarının payı
B9: =SUM(C12:G12) | D9: ='1.Reel GSYH '!F9/'1.Reel GSYH '!$B9*100
B10: Özel Tüketim (Cp) Harcamaların Reel GSYH içindeki Payı(%) | I10: Nihai Kamu Tüketim Harcamalarının Reel GSYH içindeki payı (%) | K10: Brüt Sabit Sermaye Oluşumunun Reel GSYH içindeki payının hesaplanması (%) | S10: Stok Değişimi in Reel GSYH içindeki payının hesaplanması (%) | U10: Net İhracat Reel GSYH içindeki payının hesaplanması (%)
B11: Toplam | C11: Dayanıklı Tüketim | D11: Yarı-Dayanıklı Tüketim | E11: Dayanıksız Tüketim | F11: Hizmetler | G11: Net İhracat | I11: Toplam | K11: Toplam Özel ve Kamu GFCF | L11: Toplam Kamu | M11: Makina & Ekipman (Kamu) | N11: İnşaat (Kamu) | O11: Toplam Özel | P11: Makina & Ekipman (Özel) | Q11: İnşaat (Özel) | U11: Mal ihracatı ve Hizmetler | V11: Mal ithalatı ve Hizmetler | W11: Net İhracat | X11: İhracat + İthalat
A12: Q1-1993 | B12: =SUM(C12:G12) -> #DIV/0! | C12: ='1.Reel GSYH '!E9/'1.Reel GSYH '!$B9*100 -> #DIV/0! | D12: ='1.Reel GSYH '!F9/'1.Reel GSYH '!$B9*100 -> #DIV/0! | E12: ='1.Reel GSYH '!G9/'1.Reel GSYH '!$B9*100 -> #DIV/0! | F12: ='1.Reel GSYH '!H9/'1.Reel GSYH '!$B9*100 -> #DIV/0! | G12: ='1.Reel GSYH '!I9/'1.Reel GSYH '!$B9*100 -> #DIV/0! | I12: ='1.Reel GSYH '!K9/'1.Reel GSYH '!$B9*100 -> #DIV/0! | K12: ='1.Reel GSYH '!M9/'1.Reel GSYH '!$B9*100 -> #DIV/0! | L12: ='1.Reel GSYH '!N9/'1.Reel GSYH '!$B9*100 -> #DIV/0! | M12: ='1.Reel GSYH '!O9/'1.Reel GSYH '!$B9*100 -> #DIV/0! | N12: ='1.Reel GSYH '!P9/'1.Reel GSYH '!$B9*100 -> #DIV/0! | O12: ='1.Reel GSYH '!Q9/'1.Reel GSYH '!$B9*100 -> #DIV/0! | P12: ='1.Reel GSYH '!R9/'1.Reel GSYH '!$B9*100 -> #DIV/0! | Q12: ='1.Reel GSYH '!S9/'1.Reel GSYH '!$B9*100 -> #DIV/0! | S12: ='1.Reel GSYH '!U9/'1.Reel GSYH '!$B9*100 -> #DIV/0! | U12: ='1.Reel GSYH '!W9/'1.Reel GSYH '!$B9*100 -> #DIV/0! | V12: ='1.Reel GSYH '!X9/'1.Reel GSYH '!$B9*100 -> #DIV/0! | W12: ='1.Reel GSYH '!Y9/'1.Reel GSYH '!$B9*100 -> #DIV/0! | X12: =(U12+V12) -> #DIV/0!
A13: Q2-1993 | B13: =SUM(C13:G13) -> #DIV/0! | C13: ='1.Reel GSYH '!E10/'1.Reel GSYH '!$B10*100 -> #DIV/0! | D13: ='1.Reel GSYH '!F10/'1.Reel GSYH '!$B10*100 -> #DIV/0! | E13: ='1.Reel GSYH '!G10/'1.Reel GSYH '!$B10*100 -> #DIV/0! | F13: ='1.Reel GSYH '!H10/'1.Reel GSYH '!$B10*100 -> #DIV/0! | G13: ='1.Reel GSYH '!I10/'1.Reel GSYH '!$B10*100 -> #DIV/0! | I13: ='1.Reel GSYH '!K10/'1.Reel GSYH '!$B10*100 -> #DIV/0! | K13: ='1.Reel GSYH '!M10/'1.Reel GSYH '!$B10*100 -> #DIV/0! | L13: ='1.Reel GSYH '!N10/'1.Reel GSYH '!$B10*100 -> #DIV/0! | M13: ='1.Reel GSYH '!O10/'1.Reel GSYH '!$B10*100 -> #DIV/0! | N13: ='1.Reel GSYH '!P10/'1.Reel GSYH '!$B10*100 -> #DIV/0! | O13: ='1.Reel GSYH '!Q10/'1.Reel GSYH '!$B10*100 -> #DIV/0! | P13: ='1.Reel GSYH '!R10/'1.Reel GSYH '!$B10*100 -> #DIV/0! | Q13: ='1.Reel GSYH '!S10/'1.Reel GSYH '!$B10*100 -> #DIV/0! | S13: ='1.Reel GSYH '!U10/'1.Reel GSYH '!$B10*100 -> #DIV/0! | U13: ='1.Reel GSYH '!W10/'1.Reel GSYH '!$B10*100 -> #DIV/0! | V13: ='1.Reel GSYH '!X10/'1.Reel GSYH '!$B10*100 -> #DIV/0! | W13: ='1.Reel GSYH '!Y10/'1.Reel GSYH '!$B10*100 -> #DIV/0! | X13: =(U13+V13) -> #DIV/0!
A14: Q3-1993 | B14: =SUM(C14:G14) -> #DIV/0! | C14: ='1.Reel GSYH '!E11/'1.Reel GSYH '!$B11*100 -> #DIV/0! | D14: ='1.Reel GSYH '!F11/'1.Reel GSYH '!$B11*100 -> #DIV/0! | E14: ='1.Reel GSYH '!G11/'1.Reel GSYH '!$B11*100 -> #DIV/0! | F14: ='1.Reel GSYH '!H11/'1.Reel GSYH '!$B11*100 -> #DIV/0! | G14: ='1.Reel GSYH '!I11/'1.Reel GSYH '!$B11*100 -> #DIV/0! | I14: ='1.Reel GSYH '!K11/'1.Reel GSYH '!$B11*100 -> #DIV/0! | K14: ='1.Reel GSYH '!M11/'1.Reel GSYH '!$B11*100 -> #DIV/0! | L14: ='1.Reel GSYH '!N11/'1.Reel GSYH '!$B11*100 -> #DIV/0! | M14: ='1.Reel GSYH '!O11/'1.Reel GSYH '!$B11*100 -> #DIV/0! | N14: ='1.Reel GSYH '!P11/'1.Reel GSYH '!$B11*100 -> #DIV/0! | O14: ='1.Reel GSYH '!Q11/'1.Reel GSYH '!$B11*100 -> #DIV/0! | P14: ='1.Reel GSYH '!R11/'1.Reel GSYH '!$B11*100 -> #DIV/0! | Q14: ='1.Reel GSYH '!S11/'1.Reel GSYH '!$B11*100 -> #DIV/0! | S14: ='1.Reel GSYH '!U11/'1.Reel GSYH '!$B11*100 -> #DIV/0! | U14: ='1.Reel GSYH '!W11/'1.Reel GSYH '!$B11*100 -> #DIV/0! | V14: ='1.Reel GSYH '!X11/'1.Reel GSYH '!$B11*100 -> #DIV/0! | W14: ='1.Reel GSYH '!Y11/'1.Reel GSYH '!$B11*100 -> #DIV/0! | X14: =(U14+V14) -> #DIV/0!
A15: Q4-1993 | B15: =SUM(C15:G15) -> #DIV/0! | C15: ='1.Reel GSYH '!E12/'1.Reel GSYH '!B12*100 -> #DIV/0! | D15: ='1.Reel GSYH '!F12/'1.Reel GSYH '!$B12*100 -> #DIV/0! | E15: ='1.Reel GSYH '!G12/'1.Reel GSYH '!$B12*100 -> #DIV/0! | F15: ='1.Reel GSYH '!H12/'1.Reel GSYH '!$B12*100 -> #DIV/0! | G15: ='1.Reel GSYH '!I12/'1.Reel GSYH '!$B12*100 -> #DIV/0! | I15: ='1.Reel GSYH '!K12/'1.Reel GSYH '!$B12*100 -> #DIV/0! | K15: ='1.Reel GSYH '!M12/'1.Reel GSYH '!$B12*100 -> #DIV/0! | L15: ='1.Reel GSYH '!N12/'1.Reel GSYH '!$B12*100 -> #DIV/0! | M15: ='1.Reel GSYH '!O12/'1.Reel GSYH '!$B12*100 -> #DIV/0! | N15: ='1.Reel GSYH '!P12/'1.Reel GSYH '!$B12*100 -> #DIV/0! | O15: ='1.Reel GSYH '!Q12/'1.Reel GSYH '!$B12*100 -> #DIV/0! | P15: ='1.Reel GSYH '!R12/'1.Reel GSYH '!$B12*100 -> #DIV/0! | Q15: ='1.Reel GSYH '!S12/'1.Reel GSYH '!$B12*100 -> #DIV/0! | S15: ='1.Reel GSYH '!U12/'1.Reel GSYH '!$B12*100 -> #DIV/0! | U15: ='1.Reel GSYH '!W12/'1.Reel GSYH '!$B12*100 -> #DIV/0! | V15: ='1.Reel GSYH '!X12/'1.Reel GSYH '!$B12*100 -> #DIV/0! | W15: ='1.Reel GSYH '!Y12/'1.Reel GSYH '!$B12*100 -> #DIV/0! | X15: =(U15+V15) -> #DIV/0!
A16: Q1-1994 | B16: =SUM(C16:G16) -> #DIV/0! | C16: ='1.Reel GSYH '!E13/'1.Reel GSYH '!B13*100 -> #DIV/0! | D16: ='1.Reel GSYH '!F13/'1.Reel GSYH '!$B13*100 -> #DIV/0! | E16: ='1.Reel GSYH '!G13/'1.Reel GSYH '!$B13*100 -> #DIV/0! | F16: ='1.Reel GSYH '!H13/'1.Reel GSYH '!$B13*100 -> #DIV/0! | G16: ='1.Reel GSYH '!I13/'1.Reel GSYH '!$B13*100 -> #DIV/0! | I16: ='1.Reel GSYH '!K13/'1.Reel GSYH '!$B13*100 -> #DIV/0! | K16: ='1.Reel GSYH '!M13/'1.Reel GSYH '!$B13*100 -> #DIV/0! | L16: ='1.Reel GSYH '!N13/'1.Reel GSYH '!$B13*100 -> #DIV/0! | M16: ='1.Reel GSYH '!O13/'1.Reel GSYH '!$B13*100 -> #DIV/0! | N16: ='1.Reel GSYH '!P13/'1.Reel GSYH '!$B13*100 -> #DIV/0! | O16: ='1.Reel GSYH '!Q13/'1.Reel GSYH '!$B13*100 -> #DIV/0! | P16: ='1.Reel GSYH '!R13/'1.Reel GSYH '!$B13*100 -> #DIV/0! | Q16: ='1.Reel GSYH '!S13/'1.Reel GSYH '!$B13*100 -> #DIV/0! | S16: ='1.Reel GSYH '!U13/'1.Reel GSYH '!$B13*100 -> #DIV/0! | U16: ='1.Reel GSYH '!W13/'1.Reel GSYH '!$B13*100 -> #DIV/0! | V16: ='1.Reel GSYH '!X13/'1.Reel GSYH '!$B13*100 -> #DIV/0! | W16: ='1.Reel GSYH '!Y13/'1.Reel GSYH '!$B13*100 -> #DIV/0! | X16: =(U16+V16) -> #DIV/0!
A17: Q2-1994 | B17: =SUM(C17:G17) -> #DIV/0! | C17: ='1.Reel GSYH '!E14/'1.Reel GSYH '!B14*100 -> #DIV/0! | D17: ='1.Reel GSYH '!F14/'1.Reel GSYH '!$B14*100 -> #DIV/0! | E17: ='1.Reel GSYH '!G14/'1.Reel GSYH '!$B14*100 -> #DIV/0! | F17: ='1.Reel GSYH '!H14/'1.Reel GSYH '!$B14*100 -> #DIV/0! | G17: ='1.Reel GSYH '!I14/'1.Reel GSYH '!$B14*100 -> #DIV/0! | I17: ='1.Reel GSYH '!K14/'1.Reel GSYH '!$B14*100 -> #DIV/0! | K17: ='1.Reel GSYH '!M14/'1.Reel GSYH '!$B14*100 -> #DIV/0! | L17: ='1.Reel GSYH '!N14/'1.Reel GSYH '!$B14*100 -> #DIV/0! | M17: ='1.Reel GSYH '!O14/'1.Reel GSYH '!$B14*100 -> #DIV/0! | N17: ='1.Reel GSYH '!P14/'1.Reel GSYH '!$B14*100 -> #DIV/0! | O17: ='1.Reel GSYH '!Q14/'1.Reel GSYH '!$B14*100 -> #DIV/0! | P17: ='1.Reel GSYH '!R14/'1.Reel GSYH '!$B14*100 -> #DIV/0! | Q17: ='1.Reel GSYH '!S14/'1.Reel GSYH '!$B14*100 -> #DIV/0! | S17: ='1.Reel GSYH '!U14/'1.Reel GSYH '!$B14*100 -> #DIV/0! | U17: ='1.Reel GSYH '!W14/'1.Reel GSYH '!$B14*100 -> #DIV/0! | V17: ='1.Reel GSYH '!X14/'1.Reel GSYH '!$B14*100 -> #DIV/0! | W17: ='1.Reel GSYH '!Y14/'1.Reel GSYH '!$B14*100 -> #DIV/0! | X17: =(U17+V17) -> #DIV/0!
A18: Q3-1994 | B18: =SUM(C18:G18) -> #DIV/0! | C18: ='1.Reel GSYH '!E15/'1.Reel GSYH '!B15*100 -> #DIV/0! | D18: ='1.Reel GSYH '!F15/'1.Reel GSYH '!$B15*100 -> #DIV/0! | E18: ='1.Reel GSYH '!G15/'1.Reel GSYH '!$B15*100 -> #DIV/0! | F18: ='1.Reel GSYH '!H15/'1.Reel GSYH '!$B15*100 -> #DIV/0! | G18: ='1.Reel GSYH '!I15/'1.Reel GSYH '!$B15*100 -> #DIV/0! | I18: ='1.Reel GSYH '!K15/'1.Reel GSYH '!$B15*100 -> #DIV/0! | K18: ='1.Reel GSYH '!M15/'1.Reel GSYH '!$B15*100 -> #DIV/0! | L18: ='1.Reel GSYH '!N15/'1.Reel GSYH '!$B15*100 -> #DIV/0! | M18: ='1.Reel GSYH '!O15/'1.Reel GSYH '!$B15*100 -> #DIV/0! | N18: ='1.Reel GSYH '!P15/'1.Reel GSYH '!$B15*100 -> #DIV/0! | O18: ='1.Reel GSYH '!Q15/'1.Reel GSYH '!$B15*100 -> #DIV/0! | P18: ='1.Reel GSYH '!R15/'1.Reel GSYH '!$B15*100 -> #DIV/0! | Q18: ='1.Reel GSYH '!S15/'1.Reel GSYH '!$B15*100 -> #DIV/0! | S18: ='1.Reel GSYH '!U15/'1.Reel GSYH '!$B15*100 -> #DIV/0! | U18: ='1.Reel GSYH '!W15/'1.Reel GSYH '!$B15*100 -> #DIV/0! | V18: ='1.Reel GSYH '!X15/'1.Reel GSYH '!$B15*100 -> #DIV/0! | W18: ='1.Reel GSYH '!Y15/'1.Reel GSYH '!$B15*100 -> #DIV/0! | X18: =(U18+V18) -> #DIV/0!
A19: Q4-1994 | B19: =SUM(C19:G19) -> #DIV/0! | C19: ='1.Reel GSYH '!E16/'1.Reel GSYH '!B16*100 -> #DIV/0! | D19: ='1.Reel GSYH '!F16/'1.Reel GSYH '!$B16*100 -> #DIV/0! | E19: ='1.Reel GSYH '!G16/'1.Reel GSYH '!$B16*100 -> #DIV/0! | F19: ='1.Reel GSYH '!H16/'1.Reel GSYH '!$B16*100 -> #DIV/0! | G19: ='1.Reel GSYH '!I16/'1.Reel GSYH '!$B16*100 -> #DIV/0! | I19: ='1.Reel GSYH '!K16/'1.Reel GSYH '!$B16*100 -> #DIV/0! | K19: ='1.Reel GSYH '!M16/'1.Reel GSYH '!$B16*100 -> #DIV/0! | L19: ='1.Reel GSYH '!N16/'1.Reel GSYH '!$B16*100 -> #DIV/0! | M19: ='1.Reel GSYH '!O16/'1.Reel GSYH '!$B16*100 -> #DIV/0! | N19: ='1.Reel GSYH '!P16/'1.Reel GSYH '!$B16*100 -> #DIV/0! | O19: ='1.Reel GSYH '!Q16/'1.Reel GSYH '!$B16*100 -> #DIV/0! | P19: ='1.Reel GSYH '!R16/'1.Reel GSYH '!$B16*100 -> #DIV/0! | Q19: ='1.Reel GSYH '!S16/'1.Reel GSYH '!$B16*100 -> #DIV/0! | S19: ='1.Reel GSYH '!U16/'1.Reel GSYH '!$B16*100 -> #DIV/0! | U19: ='1.Reel GSYH '!W16/'1.Reel GSYH '!$B16*100 -> #DIV/0! | V19: ='1.Reel GSYH '!X16/'1.Reel GSYH '!$B16*100 -> #DIV/0! | W19: ='1.Reel GSYH '!Y16/'1.Reel GSYH '!$B16*100 -> #DIV/0! | X19: =(U19+V19) -> #DIV/0!
A20: Q1-1995 | B20: =SUM(C20:G20) -> #DIV/0! | C20: ='1.Reel GSYH '!E17/'1.Reel GSYH '!B17*100 -> #DIV/0! | D20: ='1.Reel GSYH '!F17/'1.Reel GSYH '!$B17*100 -> #DIV/0! | E20: ='1.Reel GSYH '!G17/'1.Reel GSYH '!$B17*100 -> #DIV/0! | F20: ='1.Reel GSYH '!H17/'1.Reel GSYH '!$B17*100 -> #DIV/0! | G20: ='1.Reel GSYH '!I17/'1.Reel GSYH '!$B17*100 -> #DIV/0! | I20: ='1.Reel GSYH '!K17/'1.Reel GSYH '!$B17*100 -> #DIV/0! | K20: ='1.Reel GSYH '!M17/'1.Reel GSYH '!$B17*100 -> #DIV/0! | L20: ='1.Reel GSYH '!N17/'1.Reel GSYH '!$B17*100 -> #DIV/0! | M20: ='1.Reel GSYH '!O17/'1.Reel GSYH '!$B17*100 -> #DIV/0! | N20: ='1.Reel GSYH '!P17/'1.Reel GSYH '!$B17*100 -> #DIV/0! | O20: ='1.Reel GSYH '!Q17/'1.Reel GSYH '!$B17*100 -> #DIV/0! | P20: ='1.Reel GSYH '!R17/'1.Reel GSYH '!$B17*100 -> #DIV/0! | Q20: ='1.Reel GSYH '!S17/'1.Reel GSYH '!$B17*100 -> #DIV/0! | S20: ='1.Reel GSYH '!U17/'1.Reel GSYH '!$B17*100 -> #DIV/0! | U20: ='1.Reel GSYH '!W17/'1.Reel GSYH '!$B17*100 -> #DIV/0! | V20: ='1.Reel GSYH '!X17/'1.Reel GSYH '!$B17*100 -> #DIV/0! | W20: ='1.Reel GSYH '!Y17/'1.Reel GSYH '!$B17*100 -> #DIV/0! | X20: =(U20+V20) -> #DIV/0!
A21: Q2-1995 | B21: =SUM(C21:G21) -> #DIV/0! | C21: ='1.Reel GSYH '!E18/'1.Reel GSYH '!B18*100 -> #DIV/0! | D21: ='1.Reel GSYH '!F18/'1.Reel GSYH '!$B18*100 -> #DIV/0! | E21: ='1.Reel GSYH '!G18/'1.Reel GSYH '!$B18*100 -> #DIV/0! | F21: ='1.Reel GSYH '!H18/'1.Reel GSYH '!$B18*100 -> #DIV/0! | G21: ='1.Reel GSYH '!I18/'1.Reel GSYH '!$B18*100 -> #DIV/0! | I21: ='1.Reel GSYH '!K18/'1.Reel GSYH '!$B18*100 -> #DIV/0! | K21: ='1.Reel GSYH '!M18/'1.Reel GSYH '!$B18*100 -> #DIV/0! | L21: ='1.Reel GSYH '!N18/'1.Reel GSYH '!$B18*100 -> #DIV/0! | M21: ='1.Reel GSYH '!O18/'1.Reel GSYH '!$B18*100 -> #DIV/0! | N21: ='1.Reel GSYH '!P18/'1.Reel GSYH '!$B18*100 -> #DIV/0! | O21: ='1.Reel GSYH '!Q18/'1.Reel GSYH '!$B18*100 -> #DIV/0! | P21: ='1.Reel GSYH '!R18/'1.Reel GSYH '!$B18*100 -> #DIV/0! | Q21: ='1.Reel GSYH '!S18/'1.Reel GSYH '!$B18*100 -> #DIV/0! | S21: ='1.Reel GSYH '!U18/'1.Reel GSYH '!$B18*100 -> #DIV/0! | U21: ='1.Reel GSYH '!W18/'1.Reel GSYH '!$B18*100 -> #DIV/0! | V21: ='1.Reel GSYH '!X18/'1.Reel GSYH '!$B18*100 -> #DIV/0! | W21: ='1.Reel GSYH '!Y18/'1.Reel GSYH '!$B18*100 -> #DIV/0! | X21: =(U21+V21) -> #DIV/0!
A22: Q3-1995 | B22: =SUM(C22:G22) -> #DIV/0! | C22: ='1.Reel GSYH '!E19/'1.Reel GSYH '!B19*100 -> #DIV/0! | D22: ='1.Reel GSYH '!F19/'1.Reel GSYH '!$B19*100 -> #DIV/0! | E22: ='1.Reel GSYH '!G19/'1.Reel GSYH '!$B19*100 -> #DIV/0! | F22: ='1.Reel GSYH '!H19/'1.Reel GSYH '!$B19*100 -> #DIV/0! | G22: ='1.Reel GSYH '!I19/'1.Reel GSYH '!$B19*100 -> #DIV/0! | I22: ='1.Reel GSYH '!K19/'1.Reel GSYH '!$B19*100 -> #DIV/0! | K22: ='1.Reel GSYH '!M19/'1.Reel GSYH '!$B19*100 -> #DIV/0! | L22: ='1.Reel GSYH '!N19/'1.Reel GSYH '!$B19*100 -> #DIV/0! | M22: ='1.Reel GSYH '!O19/'1.Reel GSYH '!$B19*100 -> #DIV/0! | N22: ='1.Reel GSYH '!P19/'1.Reel GSYH '!$B19*100 -> #DIV/0! | O22: ='1.Reel GSYH '!Q19/'1.Reel GSYH '!$B19*100 -> #DIV/0! | P22: ='1.Reel GSYH '!R19/'1.Reel GSYH '!$B19*100 -> #DIV/0! | Q22: ='1.Reel GSYH '!S19/'1.Reel GSYH '!$B19*100 -> #DIV/0! | S22: ='1.Reel GSYH '!U19/'1.Reel GSYH '!$B19*100 -> #DIV/0! | U22: ='1.Reel GSYH '!W19/'1.Reel GSYH '!$B19*100 -> #DIV/0! | V22: ='1.Reel GSYH '!X19/'1.Reel GSYH '!$B19*100 -> #DIV/0! | W22: ='1.Reel GSYH '!Y19/'1.Reel GSYH '!$B19*100 -> #DIV/0! | X22: =(U22+V22) -> #DIV/0!
A23: Q4-1995 | B23: =SUM(C23:G23) -> #DIV/0! | C23: ='1.Reel GSYH '!E20/'1.Reel GSYH '!B20*100 -> #DIV/0! | D23: ='1.Reel GSYH '!F20/'1.Reel GSYH '!$B20*100 -> #DIV/0! | E23: ='1.Reel GSYH '!G20/'1.Reel GSYH '!$B20*100 -> #DIV/0! | F23: ='1.Reel GSYH '!H20/'1.Reel GSYH '!$B20*100 -> #DIV/0! | G23: ='1.Reel GSYH '!I20/'1.Reel GSYH '!$B20*100 -> #DIV/0! | I23: ='1.Reel GSYH '!K20/'1.Reel GSYH '!$B20*100 -> #DIV/0! | K23: ='1.Reel GSYH '!M20/'1.Reel GSYH '!$B20*100 -> #DIV/0! | L23: ='1.Reel GSYH '!N20/'1.Reel GSYH '!$B20*100 -> #DIV/0! | M23: ='1.Reel GSYH '!O20/'1.Reel GSYH '!$B20*100 -> #DIV/0! | N23: ='1.Reel GSYH '!P20/'1.Reel GSYH '!$B20*100 -> #DIV/0! | O23: ='1.Reel GSYH '!Q20/'1.Reel GSYH '!$B20*100 -> #DIV/0! | P23: ='1.Reel GSYH '!R20/'1.Reel GSYH '!$B20*100 -> #DIV/0! | Q23: ='1.Reel GSYH '!S20/'1.Reel GSYH '!$B20*100 -> #DIV/0! | S23: ='1.Reel GSYH '!U20/'1.Reel GSYH '!$B20*100 -> #DIV/0! | U23: ='1.Reel GSYH '!W20/'1.Reel GSYH '!$B20*100 -> #DIV/0! | V23: ='1.Reel GSYH '!X20/'1.Reel GSYH '!$B20*100 -> #DIV/0! | W23: ='1.Reel GSYH '!Y20/'1.Reel GSYH '!$B20*100 -> #DIV/0! | X23: =(U23+V23) -> #DIV/0!
A24: Q1-1996 | B24: =SUM(C24:G24) -> #DIV/0! | C24: ='1.Reel GSYH '!E21/'1.Reel GSYH '!B21*100 -> #DIV/0! | D24: ='1.Reel GSYH '!F21/'1.Reel GSYH '!$B21*100 -> #DIV/0! | E24: ='1.Reel GSYH '!G21/'1.Reel GSYH '!$B21*100 -> #DIV/0! | F24: ='1.Reel GSYH '!H21/'1.Reel GSYH '!$B21*100 -> #DIV/0! | G24: ='1.Reel GSYH '!I21/'1.Reel GSYH '!$B21*100 -> #DIV/0! | I24: ='1.Reel GSYH '!K21/'1.Reel GSYH '!$B21*100 -> #DIV/0! | K24: ='1.Reel GSYH '!M21/'1.Reel GSYH '!$B21*100 -> #DIV/0! | L24: ='1.Reel GSYH '!N21/'1.Reel GSYH '!$B21*100 -> #DIV/0! | M24: ='1.Reel GSYH '!O21/'1.Reel GSYH '!$B21*100 -> #DIV/0! | N24: ='1.Reel GSYH '!P21/'1.Reel GSYH '!$B21*100 -> #DIV/0! | O24: ='1.Reel GSYH '!Q21/'1.Reel GSYH '!$B21*100 -> #DIV/0! | P24: ='1.Reel GSYH '!R21/'1.Reel GSYH '!$B21*100 -> #DIV/0! | Q24: ='1.Reel GSYH '!S21/'1.Reel GSYH '!$B21*100 -> #DIV/0! | S24: ='1.Reel GSYH '!U21/'1.Reel GSYH '!$B21*100 -> #DIV/0! | U24: ='1.Reel GSYH '!W21/'1.Reel GSYH '!$B21*100 -> #DIV/0! | V24: ='1.Reel GSYH '!X21/'1.Reel GSYH '!$B21*100 -> #DIV/0! | W24: ='1.Reel GSYH '!Y21/'1.Reel GSYH '!$B21*100 -> #DIV/0! | X24: =(U24+V24) -> #DIV/0!
A25: Q2-1996 | B25: =SUM(C25:G25) -> #DIV/0! | C25: ='1.Reel GSYH '!E22/'1.Reel GSYH '!B22*100 -> #DIV/0! | D25: ='1.Reel GSYH '!F22/'1.Reel GSYH '!$B22*100 -> #DIV/0! | E25: ='1.Reel GSYH '!G22/'1.Reel GSYH '!$B22*100 -> #DIV/0! | F25: ='1.Reel GSYH '!H22/'1.Reel GSYH '!$B22*100 -> #DIV/0! | G25: ='1.Reel GSYH '!I22/'1.Reel GSYH '!$B22*100 -> #DIV/0! | I25: ='1.Reel GSYH '!K22/'1.Reel GSYH '!$B22*100 -> #DIV/0! | K25: ='1.Reel GSYH '!M22/'1.Reel GSYH '!$B22*100 -> #DIV/0! | L25: ='1.Reel GSYH '!N22/'1.Reel GSYH '!$B22*100 -> #DIV/0! | M25: ='1.Reel GSYH '!O22/'1.Reel GSYH '!$B22*100 -> #DIV/0! | N25: ='1.Reel GSYH '!P22/'1.Reel GSYH '!$B22*100 -> #DIV/0! | O25: ='1.Reel GSYH '!Q22/'1.Reel GSYH '!$B22*100 -> #DIV/0! | P25: ='1.Reel GSYH '!R22/'1.Reel GSYH '!$B22*100 -> #DIV/0! | Q25: ='1.Reel GSYH '!S22/'1.Reel GSYH '!$B22*100 -> #DIV/0! | S25: ='1.Reel GSYH '!U22/'1.Reel GSYH '!$B22*100 -> #DIV/0! | U25: ='1.Reel GSYH '!W22/'1.Reel GSYH '!$B22*100 -> #DIV/0! | V25: ='1.Reel GSYH '!X22/'1.Reel GSYH '!$B22*100 -> #DIV/0! | W25: ='1.Reel GSYH '!Y22/'1.Reel GSYH '!$B22*100 -> #DIV/0! | X25: =(U25+V25) -> #DIV/0!
A26: Q3-1996 | B26: =SUM(C26:G26) -> #DIV/0! | C26: ='1.Reel GSYH '!E23/'1.Reel GSYH '!B23*100 -> #DIV/0! | D26: ='1.Reel GSYH '!F23/'1.Reel GSYH '!$B23*100 -> #DIV/0! | E26: ='1.Reel GSYH '!G23/'1.Reel GSYH '!$B23*100 -> #DIV/0! | F26: ='1.Reel GSYH '!H23/'1.Reel GSYH '!$B23*100 -> #DIV/0! | G26: ='1.Reel GSYH '!I23/'1.Reel GSYH '!$B23*100 -> #DIV/0! | I26: ='1.Reel GSYH '!K23/'1.Reel GSYH '!$B23*100 -> #DIV/0! | K26: ='1.Reel GSYH '!M23/'1.Reel GSYH '!$B23*100 -> #DIV/0! | L26: ='1.Reel GSYH '!N23/'1.Reel GSYH '!$B23*100 -> #DIV/0! | M26: ='1.Reel GSYH '!O23/'1.Reel GSYH '!$B23*100 -> #DIV/0! | N26: ='1.Reel GSYH '!P23/'1.Reel GSYH '!$B23*100 -> #DIV/0! | O26: ='1.Reel GSYH '!Q23/'1.Reel GSYH '!$B23*100 -> #DIV/0! | P26: ='1.Reel GSYH '!R23/'1.Reel GSYH '!$B23*100 -> #DIV/0! | Q26: ='1.Reel GSYH '!S23/'1.Reel GSYH '!$B23*100 -> #DIV/0! | S26: ='1.Reel GSYH '!U23/'1.Reel GSYH '!$B23*100 -> #DIV/0! | U26: ='1.Reel GSYH '!W23/'1.Reel GSYH '!$B23*100 -> #DIV/0! | V26: ='1.Reel GSYH '!X23/'1.Reel GSYH '!$B23*100 -> #DIV/0! | W26: ='1.Reel GSYH '!Y23/'1.Reel GSYH '!$B23*100 -> #DIV/0! | X26: =(U26+V26) -> #DIV/0!
... A75: Q4-2008 | B75: =SUM(C75:G75) -> #DIV/0! | C75: ='1.Reel GSYH '!E72/'1.Reel GSYH '!B72*100 -> #DIV/0! | D75: ='1.Reel GSYH '!F72/'1.Reel GSYH '!$B72*100 -> #DIV/0! | E75: ='1.Reel GSYH '!G72/'1.Reel GSYH '!$B72*100 -> #DIV/0! | F75: ='1.Reel GSYH '!H72/'1.Reel GSYH '!$B72*100 -> #DIV/0! | G75: ='1.Reel GSYH '!I72/'1.Reel GSYH '!$B72*100 -> #DIV/0! | I75: ='1.Reel GSYH '!K72/'1.Reel GSYH '!$B72*100 -> #DIV/0! | K75: ='1.Reel GSYH '!M72/'1.Reel GSYH '!$B72*100 -> #DIV/0! | L75: ='1.Reel GSYH '!N72/'1.Reel GSYH '!$B72*100 -> #DIV/0! | M75: ='1.Reel GSYH '!O72/'1.Reel GSYH '!$B72*100 -> #DIV/0! | N75: ='1.Reel GSYH '!P72/'1.Reel GSYH '!$B72*100 -> #DIV/0! | O75: ='1.Reel GSYH '!Q72/'1.Reel GSYH '!$B72*100 -> #DIV/0! | P75: ='1.Reel GSYH '!R72/'1.Reel GSYH '!$B72*100 -> #DIV/0! | Q75: ='1.Reel GSYH '!S72/'1.Reel GSYH '!$B72*100 -> #DIV/0! | S75: ='1.Reel GSYH '!U72/'1.Reel GSYH '!$B72*100 -> #DIV/0! | U75: ='1.Reel GSYH '!W72/'1.Reel GSYH '!$B72*100 -> #DIV/0! | V75: ='1.Reel GSYH '!X72/'1.Reel GSYH '!$B72*100 -> #DIV/0! | W75: ='1.Reel GSYH '!Y72/'1.Reel GSYH '!$B72*100 -> #DIV/0! | X75: =(U75+V75) -> #DIV/0!
A76: Q1-2009 | B76: =SUM(C76:G76) -> 133815.6 | D76: 15446.1 | E76: 46185.9 | F76: 72183.6 | G76: ='1.Reel GSYH '!I73/'1.Reel GSYH '!$B73*100 -> 0.00031201858 | I76: ='1.Reel GSYH '!K73/'1.Reel GSYH '!$B73*100 -> 89.196995 | K76: ='1.Reel GSYH '!M73/'1.Reel GSYH '!$B73*100 -> 0 | L76: ='1.Reel GSYH '!N73/'1.Reel GSYH '!$B73*100 -> 0 | M76: ='1.Reel GSYH '!O73/'1.Reel GSYH '!$B73*100 -> 0 | N76: ='1.Reel GSYH '!P73/'1.Reel GSYH '!$B73*100 -> 0 | O76: ='1.Reel GSYH '!Q73/'1.Reel GSYH '!$B73*100 -> 0 | P76: ='1.Reel GSYH '!R73/'1.Reel GSYH '!$B73*100 -> 0 | Q76: ='1.Reel GSYH '!S73/'1.Reel GSYH '!$B73*100 -> 0 | S76: ='1.Reel GSYH '!U73/'1.Reel GSYH '!$B73*100 -> 0 | U76: ='1.Reel GSYH '!W73/'1.Reel GSYH '!$B73*100 -> 141.75695 | V76: ='1.Reel GSYH '!X73/'1.Reel GSYH '!$B73*100 -> 130.9546 | W76: ='1.Reel GSYH '!Y73/'1.Reel GSYH '!$B73*100 -> 10.802349 | X76: =(U76+V76) -> 272.71155
A77: Q2-2009 | B77: =SUM(C77:G77) -> 158937.4 | C77: 13867.4 | D77: 14821.1 | E77: 54581.3 | F77: 75667.6 | G77: ='1.Reel GSYH '!I74/'1.Reel GSYH '!$B74*100 -> 0.00038478961 | I77: ='1.Reel GSYH '!K74/'1.Reel GSYH '!$B74*100 -> 102.1171 | K77: ='1.Reel GSYH '!M74/'1.Reel GSYH '!$B74*100 -> 0 | L77: ='1.Reel GSYH '!N74/'1.Reel GSYH '!$B74*100 -> 0 | M77: ='1.Reel GSYH '!O74/'1.Reel GSYH '!$B74*100 -> 0 | N77: ='1.Reel GSYH '!P74/'1.Reel GSYH '!$B74*100 -> 0 | O77: ='1.Reel GSYH '!Q74/'1.Reel GSYH '!$B74*100 -> 0 | P77: ='1.Reel GSYH '!R74/'1.Reel GSYH '!$B74*100 -> 0 | Q77: ='1.Reel GSYH '!S74/'1.Reel GSYH '!$B74*100 -> 0 | S77: ='1.Reel GSYH '!U74/'1.Reel GSYH '!$B74*100 -> 0 | U77: ='1.Reel GSYH '!W74/'1.Reel GSYH '!$B74*100 -> 145.54001 | V77: ='1.Reel GSYH '!X74/'1.Reel GSYH '!$B74*100 -> 147.65792 | W77: ='1.Reel GSYH '!Y74/'1.Reel GSYH '!$B74*100 -> -2.117913 | X77: =(U77+V77) -> 293.19793
A78: Q3-2009 | B78: =SUM(C78:G78) -> 176619.3 | C78: 13070.6 | D78: 16667.7 | E78: 68853.6 | F78: 78027.4 | G78: ='1.Reel GSYH '!I75/'1.Reel GSYH '!$B75*100 -> 0.00042614615 | I78: ='1.Reel GSYH '!K75/'1.Reel GSYH '!$B75*100 -> 103.09519 | K78: ='1.Reel GSYH '!M75/'1.Reel GSYH '!$B75*100 -> 0 | L78: ='1.Reel GSYH '!N75/'1.Reel GSYH '!$B75*100 -> 0 | M78: ='1.Reel GSYH '!O75/'1.Reel GSYH '!$B75*100 -> 0 | N78: ='1.Reel GSYH '!P75/'1.Reel GSYH '!$B75*100 -> 0 | O78: ='1.Reel GSYH '!Q75/'1.Reel GSYH '!$B75*100 -> 0 | P78: ='1.Reel GSYH '!R75/'1.Reel GSYH '!$B75*100 -> 0 | Q78: ='1.Reel GSYH '!S75/'1.Reel GSYH '!$B75*100 -> 0 | S78: ='1.Reel GSYH '!U75/'1.Reel GSYH '!$B75*100 -> 0 | U78: ='1.Reel GSYH '!W75/'1.Reel GSYH '!$B75*100 -> 157.57392 | V78: ='1.Reel GSYH '!X75/'1.Reel GSYH '!$B75*100 -> 160.67 | W78: ='1.Reel GSYH '!Y75/'1.Reel GSYH '!$B75*100 -> -3.0960802 | X78: =(U78+V78) -> 318.24393
A79: Q4-2009 | B79: =SUM(C79:G79) -> 168863.7 | C79: 13576.9 | D79: 17942.9 | E79: 57638.6 | F79: 79705.3 | G79: ='1.Reel GSYH '!I76/'1.Reel GSYH '!$B76*100 -> 0.0004041266 | I79: ='1.Reel GSYH '!K76/'1.Reel GSYH '!$B76*100 -> 107.57519 | K79: ='1.Reel GSYH '!M76/'1.Reel GSYH '!$B76*100 -> 0 | L79: ='1.Reel GSYH '!N76/'1.Reel GSYH '!$B76*100 -> 0 | M79: ='1.Reel GSYH '!O76/'1.Reel GSYH '!$B76*100 -> 0 | N79: ='1.Reel GSYH '!P76/'1.Reel GSYH '!$B76*100 -> 0 | O79: ='1.Reel GSYH '!Q76/'1.Reel GSYH '!$B76*100 -> 0 | P79: ='1.Reel GSYH '!R76/'1.Reel GSYH '!$B76*100 -> 0 | Q79: ='1.Reel GSYH '!S76/'1.Reel GSYH '!$B76*100 -> 0 | S79: ='1.Reel GSYH '!U76/'1.Reel GSYH '!$B76*100 -> 0 | U79: ='1.Reel GSYH '!W76/'1.Reel GSYH '!$B76*100 -> 154.3693 | V79: ='1.Reel GSYH '!X76/'1.Reel GSYH '!$B76*100 -> 161.94532 | W79: ='1.Reel GSYH '!Y76/'1.Reel GSYH '!$B76*100 -> -7.5760202 | X79: =(U79+V79) -> 316.31462
A80: Q1-2010 | B80: =SUM(C80:G80) -> 152261.3 | C80: 12003.8 | D80: 16858.8 | E80: 48168.8 | F80: 75229.9 | G80: ='1.Reel GSYH '!I77/'1.Reel GSYH '!$B77*100 -> 0.00043731616 | I80: ='1.Reel GSYH '!K77/'1.Reel GSYH '!$B77*100 -> 122.49929 | K80: ='1.Reel GSYH '!M77/'1.Reel GSYH '!$B77*100 -> 0 | L80: ='1.Reel GSYH '!N77/'1.Reel GSYH '!$B77*100 -> 0 | M80: ='1.Reel GSYH '!O77/'1.Reel GSYH '!$B77*100 -> 0 | N80: ='1.Reel GSYH '!P77/'1.Reel GSYH '!$B77*100 -> 0 | O80: ='1.Reel GSYH '!Q77/'1.Reel GSYH '!$B77*100 -> 0 | P80: ='1.Reel GSYH '!R77/'1.Reel GSYH '!$B77*100 -> 0 | Q80: ='1.Reel GSYH '!S77/'1.Reel GSYH '!$B77*100 -> 0 | S80: ='1.Reel GSYH '!U77/'1.Reel GSYH '!$B77*100 -> 0 | U80: ='1.Reel GSYH '!W77/'1.Reel GSYH '!$B77*100 -> 170.00207 | V80: ='1.Reel GSYH '!X77/'1.Reel GSYH '!$B77*100 -> 192.50225 | W80: ='1.Reel GSYH '!Y77/'1.Reel GSYH '!$B77*100 -> -22.500181 | X80: =(U80+V80) -> 362.50431
A81: Q2-2010 | B81: =SUM(C81:G81) -> 171770.5 | C81: 14470.4 | D81: 19772.9 | E81: 57817.9 | F81: 79709.3 | G81: ='1.Reel GSYH '!I78/'1.Reel GSYH '!$B78*100 -> 0.00049334489 | I81: ='1.Reel GSYH '!K78/'1.Reel GSYH '!$B78*100 -> 126.04798 | K81: ='1.Reel GSYH '!M78/'1.Reel GSYH '!$B78*100 -> 0 | L81: ='1.Reel GSYH '!N78/'1.Reel GSYH '!$B78*100 -> 0 | M81: ='1.Reel GSYH '!O78/'1.Reel GSYH '!$B78*100 -> 0 | N81: ='1.Reel GSYH '!P78/'1.Reel GSYH '!$B78*100 -> 0 | O81: ='1.Reel GSYH '!Q78/'1.Reel GSYH '!$B78*100 -> 0 | P81: ='1.Reel GSYH '!R78/'1.Reel GSYH '!$B78*100 -> 0 | Q81: ='1.Reel GSYH '!S78/'1.Reel GSYH '!$B78*100 -> 0 | S81: ='1.Reel GSYH '!U78/'1.Reel GSYH '!$B78*100 -> 0 | U81: ='1.Reel GSYH '!W78/'1.Reel GSYH '!$B78*100 -> 187.06511 | V81: ='1.Reel GSYH '!X78/'1.Reel GSYH '!$B78*100 -> 213.11409 | W81: ='1.Reel GSYH '!Y78/'1.Reel GSYH '!$B78*100 -> -26.048982 | X81: =(U81+V81) -> 400.1792
A82: Q3-2010 | B82: =SUM(C82:G82) -> 198720.9 | C82: 14482.6 | D82: 20155.3 | E82: 79079.9 | F82: 85003.1 | G82: ='1.Reel GSYH '!I79/'1.Reel GSYH '!$B79*100 -> 0.00066600494 | I82: ='1.Reel GSYH '!K79/'1.Reel GSYH '!$B79*100 -> 151.36875 | K82: ='1.Reel GSYH '!M79/'1.Reel GSYH '!$B79*100 -> 0 | L82: ='1.Reel GSYH '!N79/'1.Reel GSYH '!$B79*100 -> 0 | M82: ='1.Reel GSYH '!O79/'1.Reel GSYH '!$B79*100 -> 0 | N82: ='1.Reel GSYH '!P79/'1.Reel GSYH '!$B79*100 -> 0 | O82: ='1.Reel GSYH '!Q79/'1.Reel GSYH '!$B79*100 -> 0 | P82: ='1.Reel GSYH '!R79/'1.Reel GSYH '!$B79*100 -> 0 | Q82: ='1.Reel GSYH '!S79/'1.Reel GSYH '!$B79*100 -> 0 | S82: ='1.Reel GSYH '!U79/'1.Reel GSYH '!$B79*100 -> 0 | U82: ='1.Reel GSYH '!W79/'1.Reel GSYH '!$B79*100 -> 210.36328 | V82: ='1.Reel GSYH '!X79/'1.Reel GSYH '!$B79*100 -> 261.73338 | W82: ='1.Reel GSYH '!Y79/'1.Reel GSYH '!$B79*100 -> -51.370093 | X82: =(U82+V82) -> 472.09666
A83: Q4-2010 | B83: =SUM(C83:G83) -> 188966.9 | C83: 18909.4 | D83: 20018.2 | E83: 62600.9 | F83: 87438.4 | G83: ='1.Reel GSYH '!I80/'1.Reel GSYH '!$B80*100 -> 0.00070371114 | I83: ='1.Reel GSYH '!K80/'1.Reel GSYH '!$B80*100 -> 171.07035 | K83: ='1.Reel GSYH '!M80/'1.Reel GSYH '!$B80*100 -> 0 | L83: ='1.Reel GSYH '!N80/'1.Reel GSYH '!$B80*100 -> 0 | M83: ='1.Reel GSYH '!O80/'1.Reel GSYH '!$B80*100 -> 0 | N83: ='1.Reel GSYH '!P80/'1.Reel GSYH '!$B80*100 -> 0 | O83: ='1.Reel GSYH '!Q80/'1.Reel GSYH '!$B80*100 -> 0 | P83: ='1.Reel GSYH '!R80/'1.Reel GSYH '!$B80*100 -> 0 | Q83: ='1.Reel GSYH '!S80/'1.Reel GSYH '!$B80*100 -> 0 | S83: ='1.Reel GSYH '!U80/'1.Reel GSYH '!$B80*100 -> 0 | U83: ='1.Reel GSYH '!W80/'1.Reel GSYH '!$B80*100 -> 245.90924 | V83: ='1.Reel GSYH '!X80/'1.Reel GSYH '!$B80*100 -> 316.98101 | W83: ='1.Reel GSYH '!Y80/'1.Reel GSYH '!$B80*100 -> -71.071772 | X83: =(U83+V83) -> 562.89024
A84: Q1-2011 | B84: =SUM(C84:G84) -> 179730.6 | C84: 16529.5 | D84: 23137.9 | E84: 55977.4 | F84: 84085.8 | G84: ='1.Reel GSYH '!I81/'1.Reel GSYH '!$B81*100 -> 0.00087760477 | I84: ='1.Reel GSYH '!K81/'1.Reel GSYH '!$B81*100 -> 224.72948 | K84: ='1.Reel GSYH '!M81/'1.Reel GSYH '!$B81*100 -> 0 | L84: ='1.Reel GSYH '!N81/'1.Reel GSYH '!$B81*100 -> 0 | M84: ='1.Reel GSYH '!O81/'1.Reel GSYH '!$B81*100 -> 0 | N84: ='1.Reel GSYH '!P81/'1.Reel GSYH '!$B81*100 -> 0 | O84: ='1.Reel GSYH '!Q81/'1.Reel GSYH '!$B81*100 -> 0 | P84: ='1.Reel GSYH '!R81/'1.Reel GSYH '!$B81*100 -> 0 | Q84: ='1.Reel GSYH '!S81/'1.Reel GSYH '!$B81*100 -> 0 | S84: ='1.Reel GSYH '!U81/'1.Reel GSYH '!$B81*100 -> 0 | U84: ='1.Reel GSYH '!W81/'1.Reel GSYH '!$B81*100 -> 351.1071 | V84: ='1.Reel GSYH '!X81/'1.Reel GSYH '!$B81*100 -> 475.83834 | W84: ='1.Reel GSYH '!Y81/'1.Reel GSYH '!$B81*100 -> -124.73124 | X84: =(U84+V84) -> 826.94544
A85: Q2-2011 | B85: =SUM(C85:G85) -> 197761.7 | C85: 19098.9 | D85: 23366.5 | E85: 65328.2 | F85: 89968.1 | G85: ='1.Reel GSYH '!I82/'1.Reel GSYH '!$B82*100 -> 0.0010482506 | I85: ='1.Reel GSYH '!K82/'1.Reel GSYH '!$B82*100 -> 243.52717 | K85: ='1.Reel GSYH '!M82/'1.Reel GSYH '!$B82*100 -> 0 | L85: ='1.Reel GSYH '!N82/'1.Reel GSYH '!$B82*100 -> 0 | M85: ='1.Reel GSYH '!O82/'1.Reel GSYH '!$B82*100 -> 0 | N85: ='1.Reel GSYH '!P82/'1.Reel GSYH '!$B82*100 -> 0 | O85: ='1.Reel GSYH '!Q82/'1.Reel GSYH '!$B82*100 -> 0 | P85: ='1.Reel GSYH '!R82/'1.Reel GSYH '!$B82*100 -> 0 | Q85: ='1.Reel GSYH '!S82/'1.Reel GSYH '!$B82*100 -> 0 | S85: ='1.Reel GSYH '!U82/'1.Reel GSYH '!$B82*100 -> 0 | U85: ='1.Reel GSYH '!W82/'1.Reel GSYH '!$B82*100 -> 388.64906 | V85: ='1.Reel GSYH '!X82/'1.Reel GSYH '!$B82*100 -> 532.1783 | W85: ='1.Reel GSYH '!Y82/'1.Reel GSYH '!$B82*100 -> -143.52924 | X85: =(U85+V85) -> 920.82736
A86: Q3-2011 | B86: =SUM(C86:G86) -> 218127.4 | C86: 17801.8 | D86: 25012.9 | E86: 82795.9 | F86: 92516.8 | G86: ='1.Reel GSYH '!I83/'1.Reel GSYH '!$B83*100 -> 0.0011007333 | I86: ='1.Reel GSYH '!K83/'1.Reel GSYH '!$B83*100 -> 225.67216 | K86: ='1.Reel GSYH '!M83/'1.Reel GSYH '!$B83*100 -> 0 | L86: ='1.Reel GSYH '!N83/'1.Reel GSYH '!$B83*100 -> 0 | M86: ='1.Reel GSYH '!O83/'1.Reel GSYH '!$B83*100 -> 0 | N86: ='1.Reel GSYH '!P83/'1.Reel GSYH '!$B83*100 -> 0 | O86: ='1.Reel GSYH '!Q83/'1.Reel GSYH '!$B83*100 -> 0 | P86: ='1.Reel GSYH '!R83/'1.Reel GSYH '!$B83*100 -> 0 | Q86: ='1.Reel GSYH '!S83/'1.Reel GSYH '!$B83*100 -> 0 | S86: ='1.Reel GSYH '!U83/'1.Reel GSYH '!$B83*100 -> 0 | U86: ='1.Reel GSYH '!W83/'1.Reel GSYH '!$B83*100 -> 419.86753 | V86: ='1.Reel GSYH '!X83/'1.Reel GSYH '!$B83*100 -> 545.54184 | W86: ='1.Reel GSYH '!Y83/'1.Reel GSYH '!$B83*100 -> -125.67431 | X86: =(U86+V86) -> 965.40937
A87: Q4-2011 | B87: =SUM(C87:G87) -> 206757.2 | C87: 19788.6 | D87: 23775.3 | E87: 68534.6 | F87: 94658.7 | G87: ='1.Reel GSYH '!I84/'1.Reel GSYH '!$B84*100 -> 0.00081169531 | I87: ='1.Reel GSYH '!K84/'1.Reel GSYH '!$B84*100 -> 184.4569 | K87: ='1.Reel GSYH '!M84/'1.Reel GSYH '!$B84*100 -> 0 | L87: ='1.Reel GSYH '!N84/'1.Reel GSYH '!$B84*100 -> 0 | M87: ='1.Reel GSYH '!O84/'1.Reel GSYH '!$B84*100 -> 0 | N87: ='1.Reel GSYH '!P84/'1.Reel GSYH '!$B84*100 -> 0 | O87: ='1.Reel GSYH '!Q84/'1.Reel GSYH '!$B84*100 -> 0 | P87: ='1.Reel GSYH '!R84/'1.Reel GSYH '!$B84*100 -> 0 | Q87: ='1.Reel GSYH '!S84/'1.Reel GSYH '!$B84*100 -> 0 | S87: ='1.Reel GSYH '!U84/'1.Reel GSYH '!$B84*100 -> 0 | U87: ='1.Reel GSYH '!W84/'1.Reel GSYH '!$B84*100 -> 320.46067 | V87: ='1.Reel GSYH '!X84/'1.Reel GSYH '!$B84*100 -> 404.91913 | W87: ='1.Reel GSYH '!Y84/'1.Reel GSYH '!$B84*100 -> -84.458457 | X87: =(U87+V87) -> 725.37981
A88: Q1-2012 | B88: =SUM(C88:G88) -> 186509.3 | C88: 15596.4 | D88: 24269.3 | E88: 61055.8 | F88: 85587.8 | G88: ='1.Reel GSYH '!I85/'1.Reel GSYH '!$B85*100 -> 0.0007042087 | I88: ='1.Reel GSYH '!K85/'1.Reel GSYH '!$B85*100 -> 175.48173 | K88: ='1.Reel GSYH '!M85/'1.Reel GSYH '!$B85*100 -> 0 | L88: ='1.Reel GSYH '!N85/'1.Reel GSYH '!$B85*100 -> 0 | M88: ='1.Reel GSYH '!O85/'1.Reel GSYH '!$B85*100 -> 0 | N88: ='1.Reel GSYH '!P85/'1.Reel GSYH '!$B85*100 -> 0 | O88: ='1.Reel GSYH '!Q85/'1.Reel GSYH '!$B85*100 -> 0 | P88: ='1.Reel GSYH '!R85/'1.Reel GSYH '!$B85*100 -> 0 | Q88: ='1.Reel GSYH '!S85/'1.Reel GSYH '!$B85*100 -> 0 | S88: ='1.Reel GSYH '!U85/'1.Reel GSYH '!$B85*100 -> 0 | U88: ='1.Reel GSYH '!W85/'1.Reel GSYH '!$B85*100 -> 304.91691 | V88: ='1.Reel GSYH '!X85/'1.Reel GSYH '!$B85*100 -> 380.39998 | W88: ='1.Reel GSYH '!Y85/'1.Reel GSYH '!$B85*100 -> -75.48307 | X88: =(U88+V88) -> 685.31688
... A106: Q3-2016 | B106: =SUM(C106:G106) -> 253664.6 | C106: 23443 | D106: 25604.2 | E106: 90550.4 | F106: 114067 | G106: ='1.Reel GSYH '!I103/'1.Reel GSYH '!$B103*100 -> 0.00048219995 | I106: ='1.Reel GSYH '!K103/'1.Reel GSYH '!$B103*100 -> 119.22321 | K106: ='1.Reel GSYH '!M103/'1.Reel GSYH '!$B103*100 -> 0 | L106: ='1.Reel GSYH '!N103/'1.Reel GSYH '!$B103*100 -> 0 | M106: ='1.Reel GSYH '!O103/'1.Reel GSYH '!$B103*100 -> 0 | N106: ='1.Reel GSYH '!P103/'1.Reel GSYH '!$B103*100 -> 0 | O106: ='1.Reel GSYH '!Q103/'1.Reel GSYH '!$B103*100 -> 0 | P106: ='1.Reel GSYH '!R103/'1.Reel GSYH '!$B103*100 -> 0 | Q106: ='1.Reel GSYH '!S103/'1.Reel GSYH '!$B103*100 -> 0 | S106: ='1.Reel GSYH '!U103/'1.Reel GSYH '!$B103*100 -> 0 | U106: ='1.Reel GSYH '!W103/'1.Reel GSYH '!$B103*100 -> 176.90826 | V106: ='1.Reel GSYH '!X103/'1.Reel GSYH '!$B103*100 -> 196.13228 | W106: ='1.Reel GSYH '!Y103/'1.Reel GSYH '!$B103*100 -> -19.224018 | X106: =(U106+V106) -> 373.04054
A109: Ortalamalar
A110: 1998-2001 | B110: =AVERAGE(B32:B47) -> #DIV/0! | C110: =AVERAGE(C32:C47) -> #DIV/0! | D110: =AVERAGE(D32:D47) -> #DIV/0! | E110: =AVERAGE(E32:E47) -> #DIV/0! | F110: =AVERAGE(F32:F47) -> #DIV/0! | G110: =AVERAGE(G32:G47) -> #DIV/0! | I110: =AVERAGE(I32:I47) -> #DIV/0! | K110: =AVERAGE(K32:K47) -> #DIV/0! | L110: =AVERAGE(L32:L47) -> #DIV/0! | M110: =AVERAGE(M32:M47) -> #DIV/0! | N110: =AVERAGE(N32:N47) -> #DIV/0! | O110: =AVERAGE(O32:O47) -> #DIV/0! | P110: =AVERAGE(P32:P47) -> #DIV/0! | Q110: =AVERAGE(Q32:Q47) -> #DIV/0! | S110: =AVERAGE(S32:S47) -> #DIV/0! | U110: =AVERAGE(U32:U47) -> #DIV/0! | V110: =AVERAGE(V32:V47) -> #DIV/0! | W110: =AVERAGE(W32:W47) -> #DIV/0! | X110: =AVERAGE(X32:X47) -> #DIV/0!
A111: 2002-2005 | B111: =AVERAGE(B48:B63) -> #DIV/0! | C111: =AVERAGE(C48:C63) -> #DIV/0! | D111: =AVERAGE(D48:D63) -> #DIV/0! | E111: =AVERAGE(E48:E63) -> #DIV/0! | F111: =AVERAGE(F48:F63) -> #DIV/0! | G111: =AVERAGE(G48:G63) -> #DIV/0! | I111: =AVERAGE(I48:I63) -> #DIV/0! | K111: =AVERAGE(K48:K63) -> #DIV/0! | L111: =AVERAGE(L48:L63) -> #DIV/0! | M111: =AVERAGE(M48:M63) -> #DIV/0! | N111: =AVERAGE(N48:N63) -> #DIV/0! | O111: =AVERAGE(O48:O63) -> #DIV/0! | P111: =AVERAGE(P48:P63) -> #DIV/0! | Q111: =AVERAGE(Q48:Q63) -> #DIV/0! | S111: =AVERAGE(S48:S63) -> #DIV/0! | U111: =AVERAGE(U48:U63) -> #DIV/0! | V111: =AVERAGE(V48:V63) -> #DIV/0! | W111: =AVERAGE(W48:W63) -> #DIV/0! | X111: =AVERAGE(X48:X63) -> #DIV/0!
A112: 2006-2009 | B112: =AVERAGE(B64:B79) -> #DIV/0! | C112: =AVERAGE(C64:C79) -> #DIV/0! | D112: =AVERAGE(D64:D79) -> #DIV/0! | E112: =AVERAGE(E64:E79) -> #DIV/0! | F112: =AVERAGE(F64:F79) -> #DIV/0! | G112: =AVERAGE(G64:G79) -> #DIV/0! | I112: =AVERAGE(I64:I79) -> #DIV/0! | K112: =AVERAGE(K64:K79) -> #DIV/0! | L112: =AVERAGE(L64:L79) -> #DIV/0! | M112: =AVERAGE(M64:M79) -> #DIV/0! | N112: =AVERAGE(N64:N79) -> #DIV/0! | O112: =AVERAGE(O64:O79) -> #DIV/0! | P112: =AVERAGE(P64:P79) -> #DIV/0! | Q112: =AVERAGE(Q64:Q79) -> #DIV/0! | S112: =AVERAGE(S64:S79) -> #DIV/0! | U112: =AVERAGE(U64:U79) -> #DIV/0! | V112: =AVERAGE(V64:V79) -> #DIV/0! | W112: =AVERAGE(W64:W79) -> #DIV/0! | X112: =AVERAGE(X64:X79) -> #DIV/0!
A113: 2010-2016 | B113: =AVERAGE(B80:B103) -> 214281.39 | C113: =AVERAGE(C80:C103) -> 21234.658 | D113: =AVERAGE(D80:D103) -> 23773.471 | E113: =AVERAGE(E80:E103) -> 70537.887 | F113: =AVERAGE(F80:F103) -> 98735.375 | G113: =AVERAGE(G80:G103) -> 0.00063275641 | I113: =AVERAGE(I80:I103) -> 151.67572 | K113: =AVERAGE(K80:K103) -> 0 | L113: =AVERAGE(L80:L103) -> 0 | M113: =AVERAGE(M80:M103) -> 0 | N113: =AVERAGE(N80:N103) -> 0 | O113: =AVERAGE(O80:O103) -> 0 | P113: =AVERAGE(P80:P103) -> 0 | Q113: =AVERAGE(Q80:Q103) -> 0 | S113: =AVERAGE(S80:S103) -> 0 | U113: =AVERAGE(U80:U103) -> 255.04249 | V113: =AVERAGE(V80:V103) -> 306.71941 | W113: =AVERAGE(W80:W103) -> -51.676915 | X113: =AVERAGE(X80:X103) -> 561.7619
B116: Reel GSYH Bileşenlerinin Payları 4-Yıl Ortalaması
B117: Category | C117: 1998-2001 | D117: 2002-2005 | E117: 2006-2009 | F117: 2010-2015
B118: Özel Tüketim | C118: =$B$110 -> #DIV/0! | D118: =$B$111 -> #DIV/0! | E118: =$B112 -> #DIV/0! | F118: =$B$113 -> 214281.39
B119: Özel Yatırım | C119: =$O110 -> #DIV/0! | D119: =$O111 -> #DIV/0! | E119: =$O112 -> #DIV/0! | F119: =$O113 -> 0
B120: Kamu Tüketimi | C120: =$I110 -> #DIV/0! | D120: =$I111 -> #DIV/0! | E120: =$I112 -> #DIV/0! | F120: =$I113 -> 151.67572
B121: Kamu Yatırımı | C121: =$L110 -> #DIV/0! | D121: =$L111 -> #DIV/0! | E121: =$L112 -> #DIV/0! | F121: =$L113 -> 0
B122: Stoklar | C122: =$S110 -> #DIV/0! | D122: =$S111 -> #DIV/0! | E122: =$S112 -> #DIV/0! | F122: =$S113 -> 0
B123: Net İhracat | C123: =$W110 -> #DIV/0! | D123: =$W111 -> #DIV/0! | E123: =$W112 -> #DIV/0! | F123: =$W113 -> -51.676915
B124: Toplam | C124: =SUM(C118:C123) -> #DIV/0! | D124: =SUM(D118:D123) -> #DIV/0! | E124: =SUM(E118:E123) -> #DIV/0! | F124: =SUM(F118:F123) -> 214381.39

Sheet 1b. Reel GSYH Pay Grafikleri
B1: Ülke Analizi
B2: Toplam Talep Analizi
B3: GSYH unsurlarının payı

Sheet 1c. Büyümeye Katkı
B1: Ülke Analizi
B2: Toplam Talep Analizi
B3: GSYH Büyümesine Katkı
K10: =(D17/D13-1)*100 | L10: =(E17/E13-1)*100 | M10: =(F17/F13-1)*100 | N10: =(G17/G13-1)*100 | O10: =(H17/H13-1)*100 | P10: =(I17/I13-1)*100 | R10: =(B17/B13-1)*100 | T10: =((D17-D13)/($B13))*100 | Y10: =((I17-I13)/($B13))*100
D11: GSYH Bileşenleri (Düzey, 2008 Fiyatları-DND Milyar) | K11: GSYH Bileşenlerinin Büyüme Oranları | T11: Reel GSYH Büyümesi Katkı ( Yıllık)
B12: Reel GSYH (Düzey, 2008 Fiyatları-DND Milyar) | D12: Özel Tüketim (Cp) | E12: Kamu Tüketimi (Cg) | F12: Kamu GFCF (Ig) | G12: Özel GFCF (Ip) | H12: Stok Değişimi (Ip) | I12: Net İhracat (NX) | K12: Özel Tüketim (Cp) | L12: Kamu Tüketimi (Cg) | M12: Kamu GFCF (Ig) | N12: Özel GFCF (Ip) | O12: Stok Değişimi (Ip) | P12: Net İhracat (NX) | R12: Reel GSYH Büyüme Oranı( yıllık % değişim) | T12: Özel Tüketimin (Cp) Büyümeye Katkısı | U12: Kamu Tüketiminin (Cg) Büyümeye Katkısı | V12: Kamu Yatırımının (Ig) Büyümeye Katkısı | W12: Özel Yatırımın (Ip) Büyümeye Katkısı | X12: Stok Değişiminin Büyümeye Katkısı | Y12: Net İhracatın (NX) Büyümeye Katkısı
A13: Q1-1993 | B13: ='1.Reel GSYH '!B9 -> 0 | D13: ='1.Reel GSYH '!D9 -> 0 | E13: ='1.Reel GSYH '!K9 -> 0 | F13: ='1.Reel GSYH '!N9 -> 0 | G13: ='1.Reel GSYH '!Q9 -> 0 | H13: ='1.Reel GSYH '!U9 -> 23.293625 | I13: ='1.Reel GSYH '!Y9 -> 0
A14: Q2-1993 | B14: ='1.Reel GSYH '!B10 -> 0 | D14: ='1.Reel GSYH '!D10 -> 0 | E14: ='1.Reel GSYH '!K10 -> 0 | F14: ='1.Reel GSYH '!N10 -> 0 | G14: ='1.Reel GSYH '!Q10 -> 0 | H14: ='1.Reel GSYH '!U10 -> 29.357175 | I14: ='1.Reel GSYH '!Y10 -> 0
A15: Q3-1993 | B15: ='1.Reel GSYH '!B11 -> 0 | D15: ='1.Reel GSYH '!D11 -> 0 | E15: ='1.Reel GSYH '!K11 -> 0 | F15: ='1.Reel GSYH '!N11 -> 0 | G15: ='1.Reel GSYH '!Q11 -> 0 | H15: ='1.Reel GSYH '!U11 -> 18.210875 | I15: ='1.Reel GSYH '!Y11 -> 0
A16: Q4-1993 | B16: ='1.Reel GSYH '!B12 -> 0 | D16: ='1.Reel GSYH '!D12 -> 0 | E16: ='1.Reel GSYH '!K12 -> 0 | F16: ='1.Reel GSYH '!N12 -> 0 | G16: ='1.Reel GSYH '!Q12 -> 0 | H16: ='1.Reel GSYH '!U12 -> 9.5901 | I16: ='1.Reel GSYH '!Y12 -> 0
A17: Q1-1994 | B17: ='1.Reel GSYH '!B13 -> 0 | D17: ='1.Reel GSYH '!D13 -> 0 | E17: ='1.Reel GSYH '!K13 -> 0 | F17: ='1.Reel GSYH '!N13 -> 0 | G17: ='1.Reel GSYH '!Q13 -> 0 | H17: ='1.Reel GSYH '!U13 -> 15.654625 | I17: ='1.Reel GSYH '!Y13 -> 0 | U17: =((E17-E13)/($B13))*100 -> #DIV/0! | V17: =((F17-F13)/($B13))*100 -> #DIV/0! | W17: =((G17-G13)/($B13))*100 -> #DIV/0! | X17: =((H17-H13)/($B13))*100 -> #DIV/0!
A18: Q2-1994 | B18: ='1.Reel GSYH '!B14 -> 0 | D18: ='1.Reel GSYH '!D14 -> 0 | E18: ='1.Reel GSYH '!K14 -> 0 | F18: ='1.Reel GSYH '!N14 -> 0 | G18: ='1.Reel GSYH '!Q14 -> 0 | H18: ='1.Reel GSYH '!U14 -> 39.951925 | I18: ='1.Reel GSYH '!Y14 -> 0 | U18: =((E18-E14)/($B14))*100 -> #DIV/0! | V18: =((F18-F14)/($B14))*100 -> #DIV/0! | W18: =((G18-G14)/($B14))*100 -> #DIV/0! | X18: =((H18-H14)/($B14))*100 -> #DIV/0!
A19: Q3-1994 | B19: ='1.Reel GSYH '!B15 -> 0 | D19: ='1.Reel GSYH '!D15 -> 0 | E19: ='1.Reel GSYH '!K15 -> 0 | F19: ='1.Reel GSYH '!N15 -> 0 | G19: ='1.Reel GSYH '!Q15 -> 0 | H19: ='1.Reel GSYH '!U15 -> 19.97175 | I19: ='1.Reel GSYH '!Y15 -> 0 | U19: =((E19-E15)/($B15))*100 -> #DIV/0! | V19: =((F19-F15)/($B15))*100 -> #DIV/0! | W19: =((G19-G15)/($B15))*100 -> #DIV/0! | X19: =((H19-H15)/($B15))*100 -> #DIV/0!
A20: Q4-1994 | B20: ='1.Reel GSYH '!B16 -> 0 | D20: ='1.Reel GSYH '!D16 -> 0 | E20: ='1.Reel GSYH '!K16 -> 0 | F20: ='1.Reel GSYH '!N16 -> 0 | G20: ='1.Reel GSYH '!Q16 -> 0 | H20: ='1.Reel GSYH '!U16 -> 24.088725 | I20: ='1.Reel GSYH '!Y16 -> 0 | U20: =((E20-E16)/($B16))*100 -> #DIV/0! | V20: =((F20-F16)/($B16))*100 -> #DIV/0! | W20: =((G20-G16)/($B16))*100 -> #DIV/0! | X20: =((H20-H16)/($B16))*100 -> #DIV/0!
A21: Q1-1995 | B21: ='1.Reel GSYH '!B17 -> 0 | D21: ='1.Reel GSYH '!D17 -> 0 | E21: ='1.Reel GSYH '!K17 -> 0 | F21: ='1.Reel GSYH '!N17 -> 0 | G21: ='1.Reel GSYH '!Q17 -> 0 | H21: ='1.Reel GSYH '!U17 -> 26.944575 | I21: ='1.Reel GSYH '!Y17 -> 0 | U21: =((E21-E17)/($B17))*100 -> #DIV/0! | V21: =((F21-F17)/($B17))*100 -> #DIV/0! | W21: =((G21-G17)/($B17))*100 -> #DIV/0! | X21: =((H21-H17)/($B17))*100 -> #DIV/0!
A22: Q2-1995 | B22: ='1.Reel GSYH '!B18 -> 0 | D22: ='1.Reel GSYH '!D18 -> 0 | E22: ='1.Reel GSYH '!K18 -> 0 | F22: ='1.Reel GSYH '!N18 -> 0 | G22: ='1.Reel GSYH '!Q18 -> 0 | H22: ='1.Reel GSYH '!U18 -> 26.403175 | I22: ='1.Reel GSYH '!Y18 -> 0 | U22: =((E22-E18)/($B18))*100 -> #DIV/0! | V22: =((F22-F18)/($B18))*100 -> #DIV/0! | W22: =((G22-G18)/($B18))*100 -> #DIV/0! | X22: =((H22-H18)/($B18))*100 -> #DIV/0!
A23: Q3-1995 | B23: ='1.Reel GSYH '!B19 -> 0 | D23: ='1.Reel GSYH '!D19 -> 0 | E23: ='1.Reel GSYH '!K19 -> 0 | F23: ='1.Reel GSYH '!N19 -> 0 | G23: ='1.Reel GSYH '!Q19 -> 0 | H23: ='1.Reel GSYH '!U19 -> 35.6198 | I23: ='1.Reel GSYH '!Y19 -> 0 | U23: =((E23-E19)/($B19))*100 -> #DIV/0! | V23: =((F23-F19)/($B19))*100 -> #DIV/0! | W23: =((G23-G19)/($B19))*100 -> #DIV/0! | X23: =((H23-H19)/($B19))*100 -> #DIV/0!
A24: Q4-1995 | B24: ='1.Reel GSYH '!B20 -> 0 | D24: ='1.Reel GSYH '!D20 -> 0 | E24: ='1.Reel GSYH '!K20 -> 0 | F24: ='1.Reel GSYH '!N20 -> 0 | G24: ='1.Reel GSYH '!Q20 -> 0 | H24: ='1.Reel GSYH '!U20 -> 41.673575 | I24: ='1.Reel GSYH '!Y20 -> 0 | U24: =((E24-E20)/($B20))*100 -> #DIV/0! | V24: =((F24-F20)/($B20))*100 -> #DIV/0! | W24: =((G24-G20)/($B20))*100 -> #DIV/0! | X24: =((H24-H20)/($B20))*100 -> #DIV/0!
A25: Q1-1996 | B25: ='1.Reel GSYH '!B21 -> 0 | D25: ='1.Reel GSYH '!D21 -> 0 | E25: ='1.Reel GSYH '!K21 -> 0 | F25: ='1.Reel GSYH '!N21 -> 0 | G25: ='1.Reel GSYH '!Q21 -> 0 | H25: ='1.Reel GSYH '!U21 -> 43.87125 | I25: ='1.Reel GSYH '!Y21 -> 0 | U25: =((E25-E21)/($B21))*100 -> #DIV/0! | V25: =((F25-F21)/($B21))*100 -> #DIV/0! | W25: =((G25-G21)/($B21))*100 -> #DIV/0! | X25: =((H25-H21)/($B21))*100 -> #DIV/0!
A26: Q2-1996 | B26: ='1.Reel GSYH '!B22 -> 0 | D26: ='1.Reel GSYH '!D22 -> 0 | E26: ='1.Reel GSYH '!K22 -> 0 | F26: ='1.Reel GSYH '!N22 -> 0 | G26: ='1.Reel GSYH '!Q22 -> 0 | H26: ='1.Reel GSYH '!U22 -> 39.57155 | I26: ='1.Reel GSYH '!Y22 -> 0 | U26: =((E26-E22)/($B22))*100 -> #DIV/0! | V26: =((F26-F22)/($B22))*100 -> #DIV/0! | W26: =((G26-G22)/($B22))*100 -> #DIV/0! | X26: =((H26-H22)/($B22))*100 -> #DIV/0!
A27: Q3-1996 | B27: ='1.Reel GSYH '!B23 -> 0 | D27: ='1.Reel GSYH '!D23 -> 0 | E27: ='1.Reel GSYH '!K23 -> 0 | F27: ='1.Reel GSYH '!N23 -> 0 | G27: ='1.Reel GSYH '!Q23 -> 0 | H27: ='1.Reel GSYH '!U23 -> 48.869275 | I27: ='1.Reel GSYH '!Y23 -> 0 | U27: =((E27-E23)/($B23))*100 -> #DIV/0! | V27: =((F27-F23)/($B23))*100 -> #DIV/0! | W27: =((G27-G23)/($B23))*100 -> #DIV/0! | X27: =((H27-H23)/($B23))*100 -> #DIV/0!
A28: Q4-1996 | B28: ='1.Reel GSYH '!B24 -> 0 | D28: ='1.Reel GSYH '!D24 -> 0 | E28: ='1.Reel GSYH '!K24 -> 0 | F28: ='1.Reel GSYH '!N24 -> 0 | G28: ='1.Reel GSYH '!Q24 -> 0 | H28: ='1.Reel GSYH '!U24 -> 48.701525 | I28: ='1.Reel GSYH '!Y24 -> 0 | U28: =((E28-E24)/($B24))*100 -> #DIV/0! | V28: =((F28-F24)/($B24))*100 -> #DIV/0! | W28: =((G28-G24)/($B24))*100 -> #DIV/0! | X28: =((H28-H24)/($B24))*100 -> #DIV/0!
... A76: Q4-2008 | B76: ='1.Reel GSYH '!B72 -> 0 | D76: ='1.Reel GSYH '!D72 -> 0 | E76: ='1.Reel GSYH '!K72 -> 34531531990 | F76: ='1.Reel GSYH '!N72 -> 0 | G76: ='1.Reel GSYH '!Q72 -> 0 | H76: ='1.Reel GSYH '!U72 -> 0 | I76: ='1.Reel GSYH '!Y72 -> -2622701490 | U76: =((E76-E72)/($B72))*100 -> #DIV/0! | V76: =((F76-F72)/($B72))*100 -> #DIV/0! | W76: =((G76-G72)/($B72))*100 -> #DIV/0! | X76: =((H76-H72)/($B72))*100 -> #DIV/0!
A77: Q1-2009 | B77: ='1.Reel GSYH '!B73 -> 4.1711555e+10 | D77: ='1.Reel GSYH '!D73 -> 273435.7 | E77: ='1.Reel GSYH '!K73 -> 37205453390 | F77: ='1.Reel GSYH '!N73 -> 0 | G77: ='1.Reel GSYH '!Q73 -> 0 | H77: ='1.Reel GSYH '!U73 -> 0 | I77: ='1.Reel GSYH '!Y73 -> 4505827700 | K77: =(D81/D77-1)*100 -> 9.7383041 | P77: =(I81/I77-1)*100 -> -268.77084 | R77: =R81 -> -39.337968 | T77: =((D81-D77)/($B77))*100 -> 6.3838426e-05 | U77: =((E77-E73)/($B73))*100 -> #DIV/0! | V77: =((F77-F73)/($B73))*100 -> #DIV/0! | W77: =((G77-G73)/($B73))*100 -> #DIV/0! | X77: =((H77-H73)/($B73))*100 -> #DIV/0!
A78: Q2-2009 | B78: ='1.Reel GSYH '!B74 -> 3.7452284e+10 | D78: ='1.Reel GSYH '!D74 -> 303049.9 | E78: ='1.Reel GSYH '!K74 -> 38245187990 | F78: ='1.Reel GSYH '!N74 -> 0 | G78: ='1.Reel GSYH '!Q74 -> 0 | H78: ='1.Reel GSYH '!U74 -> 0 | I78: ='1.Reel GSYH '!Y74 -> -793206780 | K78: =(D82/D78-1)*100 -> 11.734305 | P78: =(I82/I78-1)*100 -> 1010.5917 | R78: =(B82/B78-1)*100 -> -9.7033246 | T78: =((D82-D78)/($B78))*100 -> 9.4949616e-05 | U78: =((E78-E74)/($B74))*100 -> #DIV/0! | V78: =((F78-F74)/($B74))*100 -> #DIV/0! | W78: =((G78-G74)/($B74))*100 -> #DIV/0! | X78: =((H78-H74)/($B74))*100 -> #DIV/0!
A79: Q3-2009 | B79: ='1.Reel GSYH '!B75 -> 3.8455469e+10 | D79: ='1.Reel GSYH '!D75 -> 340495.8 | E79: ='1.Reel GSYH '!K75 -> 39645740940 | F79: ='1.Reel GSYH '!N75 -> 0 | G79: ='1.Reel GSYH '!Q75 -> 0 | H79: ='1.Reel GSYH '!U75 -> 0 | I79: ='1.Reel GSYH '!Y75 -> -1190612180 | K79: =(D83/D79-1)*100 -> 15.764159 | P79: =(I83/I79-1)*100 -> 1166.196 | R79: =(B83/B79-1)*100 -> -23.686254 | T79: =((D83-D79)/($B79))*100 -> 0.00013958041 | U79: =((E79-E75)/($B75))*100 -> #DIV/0! | V79: =((F79-F75)/($B75))*100 -> #DIV/0! | W79: =((G79-G75)/($B75))*100 -> #DIV/0! | X79: =((H79-H75)/($B75))*100 -> #DIV/0!
A80: Q4-2009 | B80: ='1.Reel GSYH '!B76 -> 3.9488665e+10 | D80: ='1.Reel GSYH '!D76 -> 328447.9 | E80: ='1.Reel GSYH '!K76 -> 42480006080 | F80: ='1.Reel GSYH '!N76 -> 0 | G80: ='1.Reel GSYH '!Q76 -> 0 | H80: ='1.Reel GSYH '!U76 -> 0 | I80: ='1.Reel GSYH '!Y76 -> -2991669250 | K80: =(D84/D80-1)*100 -> 14.185781 | P80: =(I84/I80-1)*100 -> 528.16625 | R80: =(B84/B80-1)*100 -> -33.039517 | T80: =((D84-D80)/($B80))*100 -> 0.00011799057 | U80: =((E80-E76)/($B76))*100 -> #DIV/0! | V80: =((F80-F76)/($B76))*100 -> #DIV/0! | W80: =((G80-G76)/($B76))*100 -> #DIV/0! | X80: =((H80-H76)/($B76))*100 -> #DIV/0!
A81: Q1-2010 | B81: ='1.Reel GSYH '!B77 -> 3.3797608e+10 | D81: ='1.Reel GSYH '!D77 -> 300063.7 | E81: ='1.Reel GSYH '!K77 -> 41401830940 | F81: ='1.Reel GSYH '!N77 -> 0 | G81: ='1.Reel GSYH '!Q77 -> 0 | H81: ='1.Reel GSYH '!U77 -> 0 | I81: ='1.Reel GSYH '!Y77 -> -7.6045231e+09 | K81: =(D85/D81-1)*100 -> 19.861183 | P81: =(I85/I81-1)*100 -> 236.28397 | R81: =(B85/B81-1)*100 -> -39.337968 | T81: =((D85-D81)/($B81))*100 -> 0.0001763326 | U81: =((E81-E77)/($B77))*100 -> 10.060468 | V81: =((F81-F77)/($B77))*100 -> 0 | W81: =((G81-G77)/($B77))*100 -> 0 | X81: =((H81-H77)/($B77))*100 -> 0 | Y81: =((I85-I81)/($B81))*100 -> -53.164322
A82: Q2-2010 | B82: ='1.Reel GSYH '!B78 -> 3.3818168e+10 | D82: ='1.Reel GSYH '!D78 -> 338610.7 | E82: ='1.Reel GSYH '!K78 -> 42627117410 | F82: ='1.Reel GSYH '!N78 -> 0 | G82: ='1.Reel GSYH '!Q78 -> 0 | H82: ='1.Reel GSYH '!U78 -> 0 | I82: ='1.Reel GSYH '!Y78 -> -8809288490 | K82: =(D86/D82-1)*100 -> 18.117531 | P82: =(I86/I82-1)*100 -> 214.27436 | R82: =(B86/B82-1)*100 -> -42.962652 | T82: =((D86-D82)/($B82))*100 -> 0.00018140516 | U82: =((E82-E78)/($B78))*100 -> 11.700032 | V82: =((F82-F78)/($B78))*100 -> 0 | W82: =((G82-G78)/($B78))*100 -> 0 | X82: =((H82-H78)/($B78))*100 -> 0 | Y82: =((I86-I82)/($B82))*100 -> -55.81629
A83: Q3-2010 | B83: ='1.Reel GSYH '!B79 -> 2.9346809e+10 | D83: ='1.Reel GSYH '!D79 -> 394172.1 | E83: ='1.Reel GSYH '!K79 -> 44421898300 | F83: ='1.Reel GSYH '!N79 -> 0 | G83: ='1.Reel GSYH '!Q79 -> 0 | H83: ='1.Reel GSYH '!U79 -> 0 | I83: ='1.Reel GSYH '!Y79 -> -15075483250 | K83: =(D87/D83-1)*100 -> 13.492558 | P83: =(I87/I83-1)*100 -> 73.60489 | R83: =(B87/B83-1)*100 -> -29.038008 | T83: =((D87-D83)/($B83))*100 -> 0.00018122549 | U83: =((E83-E79)/($B79))*100 -> 12.419969 | V83: =((F83-F79)/($B79))*100 -> 0 | W83: =((G83-G79)/($B79))*100 -> 0 | X83: =((H83-H79)/($B79))*100 -> 0 | Y83: =((I87-I83)/($B83))*100 -> -37.810901
A84: Q4-2010 | B84: ='1.Reel GSYH '!B80 -> 2.6441801e+10 | D84: ='1.Reel GSYH '!D80 -> 375040.8 | E84: ='1.Reel GSYH '!K80 -> 45234082450 | F84: ='1.Reel GSYH '!N80 -> 0 | G84: ='1.Reel GSYH '!Q80 -> 0 | H84: ='1.Reel GSYH '!U80 -> 0 | I84: ='1.Reel GSYH '!Y80 -> -18792656570 | K84: =(D88/D84-1)*100 -> 15.004288 | P84: =(I88/I84-1)*100 -> 24.332941 | R84: =(B88/B84-1)*100 -> 4.6261411 | T84: =((D88-D84)/($B84))*100 -> 0.00021281531 | U84: =((E84-E80)/($B80))*100 -> 6.9743466 | V84: =((F84-F80)/($B80))*100 -> 0 | W84: =((G84-G80)/($B80))*100 -> 0 | X84: =((H84-H80)/($B80))*100 -> 0 | Y84: =((I88-I84)/($B84))*100 -> -17.293852
A85: Q1-2011 | B85: ='1.Reel GSYH '!B81 -> 2.0502316e+10 | D85: ='1.Reel GSYH '!D81 -> 359659.9 | E85: ='1.Reel GSYH '!K81 -> 46074748340 | F85: ='1.Reel GSYH '!N81 -> 0 | G85: ='1.Reel GSYH '!Q81 -> 0 | H85: ='1.Reel GSYH '!U81 -> 0 | I85: ='1.Reel GSYH '!Y81 -> -25572792340 | K85: =(D89/D85-1)*100 -> 8.9517903 | P85: =(I89/I85-1)*100 -> -13.928865 | R85: =(B89/B85-1)*100 -> 42.227381 | T85: =((D89-D85)/($B85))*100 -> 0.00015703592 | U85: =((E85-E81)/($B81))*100 -> 13.826178 | V85: =((F85-F81)/($B81))*100 -> 0 | W85: =((G85-G81)/($B81))*100 -> 0 | X85: =((H85-H81)/($B81))*100 -> 0 | Y85: =((I89-I85)/($B85))*100 -> 17.373646
A86: Q2-2011 | B86: ='1.Reel GSYH '!B82 -> 1.9288986e+10 | D86: ='1.Reel GSYH '!D82 -> 399958.6 | E86: ='1.Reel GSYH '!K82 -> 46973920890 | F86: ='1.Reel GSYH '!N82 -> 0 | G86: ='1.Reel GSYH '!Q82 -> 0 | H86: ='1.Reel GSYH '!U82 -> 0 | I86: ='1.Reel GSYH '!Y82 -> -27685335060 | K86: =(D90/D86-1)*100 -> 7.4670728 | P86: =(I90/I86-1)*100 -> -41.229861 | R86: =(B90/B86-1)*100 -> 106.89095 | T86: =((D90-D86)/($B86))*100 -> 0.00015483033 | U86: =((E86-E82)/($B82))*100 -> 12.853457 | V86: =((F86-F82)/($B82))*100 -> 0 | W86: =((G86-G82)/($B82))*100 -> 0 | X86: =((H86-H82)/($B82))*100 -> 0 | Y86: =((I90-I86)/($B86))*100 -> 59.176907
A87: Q3-2011 | B87: ='1.Reel GSYH '!B83 -> 20825080286 | D87: ='1.Reel GSYH '!D83 -> 447356 | E87: ='1.Reel GSYH '!K83 -> 46996409100 | F87: ='1.Reel GSYH '!N83 -> 0 | G87: ='1.Reel GSYH '!Q83 -> 0 | H87: ='1.Reel GSYH '!U83 -> 0 | I87: ='1.Reel GSYH '!Y83 -> -26171776170 | K87: =(D91/D87-1)*100 -> 6.8593246 | P87: =(I91/I87-1)*100 -> -41.750883 | R87: =(B91/B87-1)*100 -> 104.46611 | T87: =((D91-D87)/($B87))*100 -> 0.00014734925 | U87: =((E87-E83)/($B83))*100 -> 8.7727111 | V87: =((F87-F83)/($B83))*100 -> 0 | W87: =((G87-G83)/($B83))*100 -> 0 | X87: =((H87-H83)/($B83))*100 -> 0 | Y87: =((I91-I87)/($B87))*100 -> 52.470134
A88: Q4-2011 | B88: ='1.Reel GSYH '!B84 -> 27665035933 | D88: ='1.Reel GSYH '!D84 -> 431313 | E88: ='1.Reel GSYH '!K84 -> 51030067210 | F88: ='1.Reel GSYH '!N84 -> 0 | G88: ='1.Reel GSYH '!Q84 -> 0 | H88: ='1.Reel GSYH '!U84 -> 0 | I88: ='1.Reel GSYH '!Y84 -> -23365462590 | K88: =(D92/D88-1)*100 -> 7.6557164 | P88: =(I92/I88-1)*100 -> -50.964089 | R88: =(B92/B88-1)*100 -> 69.066699 | T88: =((D92-D88)/($B88))*100 -> 0.00011935679 | U88: =((E88-E84)/($B84))*100 -> 21.919781 | V88: =((F88-F84)/($B84))*100 -> 0 | W88: =((G88-G84)/($B84))*100 -> 0 | X88: =((H88-H84)/($B84))*100 -> 0 | Y88: =((I92-I88)/($B88))*100 -> 43.043483
A89: Q1-2012 | B89: ='1.Reel GSYH '!B85 -> 2.9159907e+10 | D89: ='1.Reel GSYH '!D85 -> 391855.9 | E89: ='1.Reel GSYH '!K85 -> 51170307400 | F89: ='1.Reel GSYH '!N85 -> 0 | G89: ='1.Reel GSYH '!Q85 -> 0 | H89: ='1.Reel GSYH '!U85 -> 0 | I89: ='1.Reel GSYH '!Y85 -> -22010792620 | K89: =(D93/D89-1)*100 -> 9.8716901 | P89: =(I93/I89-1)*100 -> -2.0730709 | R89: =(B93/B89-1)*100 -> 36.608636 | T89: =((D93-D89)/($B89))*100 -> 0.00013265749 | U89: =((E89-E85)/($B85))*100 -> 24.853578 | V89: =((F89-F85)/($B85))*100 -> 0 | W89: =((G89-G85)/($B85))*100 -> 0 | X89: =((H89-H85)/($B85))*100 -> 0 | Y89: =((I93-I89)/($B89))*100 -> 1.5648176
A90: Q2-2012 | B90: ='1.Reel GSYH '!B86 -> 3.9907166e+10 | D90: ='1.Reel GSYH '!D86 -> 429823.8 | E90: ='1.Reel GSYH '!K86 -> 56177446370 | F90: ='1.Reel GSYH '!N86 -> 0 | G90: ='1.Reel GSYH '!Q86 -> 0 | H90: ='1.Reel GSYH '!U86 -> 0 | I90: ='1.Reel GSYH '!Y86 -> -16270709960 | K90: =(D94/D90-1)*100 -> 11.446877 | P90: =(I94/I90-1)*100 -> 30.463479 | R90: =(B94/B90-1)*100 -> 3.8428791 | T90: =((D94-D90)/($B90))*100 -> 0.00012328964 | U90: =((E90-E86)/($B86))*100 -> 47.71389 | V90: =((F90-F86)/($B86))*100 -> 0 | W90: =((G90-G86)/($B86))*100 -> 0 | X90: =((H90-H86)/($B86))*100 -> 0 | Y90: =((I94-I90)/($B90))*100 -> -12.420386
A91: Q3-2012 | B91: ='1.Reel GSYH '!B87 -> 4.2580232e+10 | D91: ='1.Reel GSYH '!D87 -> 478041.6 | E91: ='1.Reel GSYH '!K87 -> 57824582560 | F91: ='1.Reel GSYH '!N87 -> 0 | G91: ='1.Reel GSYH '!Q87 -> 0 | H91: ='1.Reel GSYH '!U87 -> 0 | I91: ='1.Reel GSYH '!Y87 -> -15244828560 | K91: =(D95/D91-1)*100 -> 11.562948 | P91: =(I95/I91-1)*100 -> 55.404657 | R91: =(B95/B91-1)*100 -> -1.0774464 | T91: =((D95-D91)/($B91))*100 -> 0.0001298154 | U91: =((E91-E87)/($B87))*100 -> 51.995831 | V91: =((F91-F87)/($B87))*100 -> 0 | W91: =((G91-G87)/($B87))*100 -> 0 | X91: =((H91-H87)/($B87))*100 -> 0 | Y91: =((I95-I91)/($B91))*100 -> -19.836306
A92: Q4-2012 | B92: ='1.Reel GSYH '!B88 -> 4.6772363e+10 | D92: ='1.Reel GSYH '!D88 -> 464333.1 | E92: ='1.Reel GSYH '!K88 -> 58229366140 | F92: ='1.Reel GSYH '!N88 -> 0 | G92: ='1.Reel GSYH '!Q88 -> 0 | H92: ='1.Reel GSYH '!U88 -> 0 | I92: ='1.Reel GSYH '!Y88 -> -11457467500 | K92: =(D96/D92-1)*100 -> 11.08717 | P92: =(I96/I92-1)*100 -> 106.22048 | R92: =(B96/B92-1)*100 -> -9.9484975 | T92: =((D96-D92)/($B92))*100 -> 0.00011006799 | U92: =((E92-E88)/($B88))*100 -> 26.023096 | V92: =((F92-F88)/($B88))*100 -> 0 | W92: =((G92-G88)/($B88))*100 -> 0 | X92: =((H92-H88)/($B88))*100 -> 0 | Y92: =((I96-I92)/($B92))*100 -> -26.020017
... A107: Q3-2016 | B107: ='1.Reel GSYH '!B103 -> 7.8800443e+10 | D107: ='1.Reel GSYH '!D103 -> 633640.3 | E107: ='1.Reel GSYH '!K103 -> 93948421030 | F107: ='1.Reel GSYH '!N103 -> 0 | G107: ='1.Reel GSYH '!Q103 -> 0 | H107: ='1.Reel GSYH '!U103 -> 0 | I107: ='1.Reel GSYH '!Y103 -> -15148611500 | K107: =(D111/D107-1)*100 -> -100 | P107: =(I111/I107-1)*100 -> -95.903332 | R107: =(B111/B107-1)*100 -> -100 | T107: =((D111-D107)/($B107))*100 -> -0.00080410753 | U107: =((E107-E103)/($B103))*100 -> 13.872063 | V107: =((F107-F103)/($B103))*100 -> 0 | W107: =((G107-G103)/($B103))*100 -> 0 | X107: =((H107-H103)/($B103))*100 -> 0 | Y107: =((I111-I107)/($B107))*100 -> 18.436474
A109: Ortalamalar | Q109: Dönem | R109: Reel GSYH Büyüme Oranı( yıllık % değişim) | T109: Özel Tüketim (Cp) Katkısı | U109: Kamu Tüketim (Cg) Katkısı | V109: Kamı Yatırım (Ig) Katkısı | W109: Özel Yatırım (Ip) Katkısı | X109: Stok Değişimi Katkısı | Y109: Net İhracat (NX) Katkısı
A110: 1998-2001 | B110: =AVERAGE(B32:B47) -> 0 | D110: =AVERAGE(D32:D47) -> 0 | E110: =AVERAGE(E32:E47) -> 3.9622492e+09 | F110: =AVERAGE(F32:F47) -> 0 | G110: =AVERAGE(G32:G47) -> 0 | H110: =AVERAGE(H32:H47) -> 2.2500047 | I110: =AVERAGE(I32:I47) -> 2.7615924e+08 | K110: =AVERAGE(K32:K47) -> #DIV/0! | L110: =AVERAGE(L32:L47) -> #DIV/0! | M110: =AVERAGE(M32:M47) -> #DIV/0! | N110: =AVERAGE(N32:N47) -> #DIV/0! | O110: =AVERAGE(O32:O47) -> #DIV/0! | P110: =AVERAGE(P32:P47) -> #DIV/0! | Q110: 1998-2001 | R110: =AVERAGE(R32:R47) -> #DIV/0! | T110: =AVERAGE(T32:T47) -> #DIV/0! | U110: =AVERAGE(U32:U47) -> #DIV/0! | V110: =AVERAGE(V32:V47) -> #DIV/0! | W110: =AVERAGE(W32:W47) -> #DIV/0! | X110: =AVERAGE(X32:X47) -> #DIV/0! | Y110: =AVERAGE(Y32:Y47) -> #DIV/0!
A111: 2002-2005 | B111: =AVERAGE(B48:B63) -> 0 | D111: =AVERAGE(D48:D63) -> 0 | E111: =AVERAGE(E48:E63) -> 1.5467318e+10 | F111: =AVERAGE(F48:F63) -> 0 | G111: =AVERAGE(G48:G63) -> 0 | H111: =AVERAGE(H48:H63) -> 0 | I111: =AVERAGE(I48:I63) -> -6.2058838e+08 | K111: =AVERAGE(K48:K63) -> #DIV/0! | L111: =AVERAGE(L48:L63) -> #DIV/0! | M111: =AVERAGE(M48:M63) -> #DIV/0! | N111: =AVERAGE(N48:N63) -> #DIV/0! | O111: =AVERAGE(O48:O63) -> #DIV/0! | P111: =AVERAGE(P48:P63) -> #DIV/0! | Q111: 2002-2005 | R111: =AVERAGE(R48:R63) -> #DIV/0! | T111: =AVERAGE(T48:T63) -> #DIV/0! | U111: =AVERAGE(U48:U63) -> #DIV/0! | V111: =AVERAGE(V48:V63) -> #DIV/0! | W111: =AVERAGE(W48:W63) -> #DIV/0! | X111: =AVERAGE(X48:X63) -> #DIV/0! | Y111: =AVERAGE(Y48:Y63) -> #DIV/0!
A112: 2006-2009 | B112: =AVERAGE(B64:B79) -> 7.3512068e+09 | D112: =AVERAGE(D64:D79) -> 57311.338 | E112: =AVERAGE(E64:E79) -> 3.0981599e+10 | F112: =AVERAGE(F64:F79) -> 0 | G112: =AVERAGE(G64:G79) -> 0 | H112: =AVERAGE(H64:H79) -> 0 | I112: =AVERAGE(I64:I79) -> -6.567009e+09 | K112: =AVERAGE(K64:K79) -> 12.412256 | L112: =AVERAGE(L64:L79) -> #DIV/0! | M112: =AVERAGE(M64:M79) -> #DIV/0! | N112: =AVERAGE(N64:N79) -> #DIV/0! | O112: =AVERAGE(O64:O79) -> #DIV/0! | P112: =AVERAGE(P64:P79) -> 636.0056 | Q112: 2006-2009 | R112: =AVERAGE(R64:R79) -> -24.242516 | T112: =AVERAGE(T64:T79) -> 9.9456149e-05 | U112: =AVERAGE(U64:U79) -> #DIV/0! | V112: =AVERAGE(V64:V79) -> #DIV/0! | W112: =AVERAGE(W64:W79) -> #DIV/0! | X112: =AVERAGE(X64:X79) -> #DIV/0! | Y112: =AVERAGE(Y64:Y79) -> #DIV/0!
A113: 2010-2016 | B113: =AVERAGE(B80:B103) -> 4.1467563e+10 | D113: =AVERAGE(D80:D103) -> 453901.65 | E113: =AVERAGE(E80:E103) -> 5.872981e+10 | F113: =AVERAGE(F80:F103) -> 0 | G113: =AVERAGE(G80:G103) -> 0 | H113: =AVERAGE(H80:H103) -> 0 | I113: =AVERAGE(I80:I103) -> -1.7262701e+10 | K113: =AVERAGE(K80:K103) -> 9.9619523 | L113: =AVERAGE(L80:L103) -> #DIV/0! | M113: =AVERAGE(M80:M103) -> #DIV/0! | N113: =AVERAGE(N80:N103) -> #DIV/0! | O113: =AVERAGE(O80:O103) -> #DIV/0! | P113: =AVERAGE(P80:P103) -> 41.424577 | Q113: 2010-2016 | R113: =AVERAGE(R80:R103) -> 21.412372 | T113: =AVERAGE(T80:T103) -> 0.00011650084 | U113: =AVERAGE(U80:U103) -> #DIV/0! | V113: =AVERAGE(V80:V103) -> #DIV/0! | W113: =AVERAGE(W80:W103) -> #DIV/0! | X113: =AVERAGE(X80:X103) -> #DIV/0! | Y113: =AVERAGE(Y80:Y103) -> 1.2496449

Sheet 1d. Katkı Grafikleri
B1: Ülke Analizi
B2: Toplam Talep Analizi
B3: GSYH Büyümesine Katkı

Sheet 2.Özel Tüketim
B1: Ülke Analizi
B2: Toplam Talep Analizi
B3: Özel Tüketim Analizi
K9: =(D12/$B12)*100 | L9: =E12/$B12*100 | M9: =F12/$B12*100 | N9: =G12/$B12*100 | O9: =H12/$B12*100 | P9: =I12/$B12*100 | V9: =(H16/H12-1)*100 | Y9: =(B16/B12-1)*100 | Z9: =((D16-D12)/$B12)*100 | AA9: =((E16-E12)/$B12)*100
D10: Reel Özel Tüketim Bileşenleri (Düzey, 2008 Fiyatları-DND Milyar) | K10: Real Özel Tüketim (GSYH içindeki payı %) | R10: Özel Tüketim Büyüme Oranları (% YoY) | Y10: Özel Tüketim Bileşenlerinin Büyümeye Katkısı (% YoY)
B11: Reel GSYH (Düzey, 2008 Fiyatları-DND Milyar) | D11: Toplam Özel Tüketim (Cp) | E11: Dayanıklı Tüketim | F11: Yarı-Dayanıklı Tüketim | G11: Dayanıksız Tüketim | H11: Hizmetler | I11: Net İhracat | K11: Toplam (Cp) | L11: Dayanıklı Tüketim | M11: Yarı-Dayanıklı Tüketim | N11: Dayanıksız Tüketim | O11: Hizmetler | P11: Net İhracat | R11: Toplam Özel Tüketim (Cp) | S11: Dayanıklı Tüketim | T11: Yarı Dayanıklı Tüketim | U11: Dayanıksız Tüketim | V11: Hizmetler | W11: Net İhracat | Y11: Real GSYH Büyüme Oranı | Z11: Toplam Özel Tüketim (Cp) | AA11: Dayanıklı Tüketim | AB11: Yarı Dayanıklı Tüketim | AC11: Dayanıksız Tüketim | AD11: Hizmetler | AE11: Net İhracat
A12: Q1-1993 | B12: ='1.Reel GSYH '!B9 -> 0 | D12: ='1.Reel GSYH '!D9 -> 0 | E12: ='1.Reel GSYH '!E9 -> 0 | F12: ='1.Reel GSYH '!F9 -> 0 | G12: ='1.Reel GSYH '!G9 -> 0 | H12: ='1.Reel GSYH '!H9 -> 0 | I12: ='1.Reel GSYH '!I9 -> 0 | K12: =(D12/$B12)*100 -> #DIV/0! | L12: =E12/$B12*100 -> #DIV/0! | M12: =F12/$B12*100 -> #DIV/0! | N12: =G12/$B12*100 -> #DIV/0! | O12: =H12/$B12*100 -> #DIV/0! | P12: =I12/$B12*100 -> #DIV/0!
A13: Q2-1993 | B13: ='1.Reel GSYH '!B10 -> 0 | D13: ='1.Reel GSYH '!D10 -> 0 | E13: ='1.Reel GSYH '!E10 -> 0 | F13: ='1.Reel GSYH '!F10 -> 0 | G13: ='1.Reel GSYH '!G10 -> 0 | H13: ='1.Reel GSYH '!H10 -> 0 | I13: ='1.Reel GSYH '!I10 -> 0 | K13: =(D13/B13)*100 -> #DIV/0! | L13: =E13/$B13*100 -> #DIV/0! | M13: =F13/$B13*100 -> #DIV/0! | N13: =G13/$B13*100 -> #DIV/0! | O13: =H13/$B13*100 -> #DIV/0! | P13: =I13/$B13*100 -> #DIV/0!
A14: Q3-1993 | B14: ='1.Reel GSYH '!B11 -> 0 | D14: ='1.Reel GSYH '!D11 -> 0 | E14: ='1.Reel GSYH '!E11 -> 0 | F14: ='1.Reel GSYH '!F11 -> 0 | G14: ='1.Reel GSYH '!G11 -> 0 | H14: ='1.Reel GSYH '!H11 -> 0 | I14: ='1.Reel GSYH '!I11 -> 0 | K14: =(D14/B14)*100 -> #DIV/0! | L14: =E14/$B14*100 -> #DIV/0! | M14: =F14/$B14*100 -> #DIV/0! | N14: =G14/$B14*100 -> #DIV/0! | O14: =H14/$B14*100 -> #DIV/0! | P14: =I14/$B14*100 -> #DIV/0!
A15: Q4-1993 | B15: ='1.Reel GSYH '!B12 -> 0 | D15: ='1.Reel GSYH '!D12 -> 0 | E15: ='1.Reel GSYH '!E12 -> 0 | F15: ='1.Reel GSYH '!F12 -> 0 | G15: ='1.Reel GSYH '!G12 -> 0 | H15: ='1.Reel GSYH '!H12 -> 0 | I15: ='1.Reel GSYH '!I12 -> 0 | K15: =(D15/B15)*100 -> #DIV/0! | L15: =E15/$B15*100 -> #DIV/0! | M15: =F15/$B15*100 -> #DIV/0! | N15: =G15/$B15*100 -> #DIV/0! | O15: =H15/$B15*100 -> #DIV/0! | P15: =I15/$B15*100 -> #DIV/0!
A16: Q1-1994 | B16: ='1.Reel GSYH '!B13 -> 0 | D16: ='1.Reel GSYH '!D13 -> 0 | E16: ='1.Reel GSYH '!E13 -> 0 | F16: ='1.Reel GSYH '!F13 -> 0 | G16: ='1.Reel GSYH '!G13 -> 0 | H16: ='1.Reel GSYH '!H13 -> 0 | I16: ='1.Reel GSYH '!I13 -> 0 | K16: =(D16/B16)*100 -> #DIV/0! | L16: =E16/$B16*100 -> #DIV/0! | M16: =F16/$B16*100 -> #DIV/0! | N16: =G16/$B16*100 -> #DIV/0! | O16: =H16/$B16*100 -> #DIV/0! | P16: =I16/$B16*100 -> #DIV/0! | R16: =(D16/D12-1)*100 -> #DIV/0! | S16: =(E16/E12-1)*100 -> #DIV/0! | T16: =(F16/F12-1)*100 -> #DIV/0! | U16: =(G16/G12-1)*100 -> #DIV/0! | V16: =(H16/H12-1)*100 -> #DIV/0! | W16: =(I16/I12-1)*100 -> #DIV/0! | Y16: =(B16/B12-1)*100 -> #DIV/0! | Z16: =((D16-D12)/$B12)*100 -> #DIV/0! | AA16: =((E16-E12)/$B12)*100 -> #DIV/0! | AB16: =((F16-F12)/$B12)*100 -> #DIV/0! | AC16: =((G16-G12)/$B12)*100 -> #DIV/0! | AD16: =((H16-H12)/$B12)*100 -> #DIV/0! | AE16: =((I16-I12)/$B12)*100 -> #DIV/0!
A17: Q2-1994 | B17: ='1.Reel GSYH '!B14 -> 0 | D17: ='1.Reel GSYH '!D14 -> 0 | E17: ='1.Reel GSYH '!E14 -> 0 | F17: ='1.Reel GSYH '!F14 -> 0 | G17: ='1.Reel GSYH '!G14 -> 0 | H17: ='1.Reel GSYH '!H14 -> 0 | I17: ='1.Reel GSYH '!I14 -> 0 | K17: =(D17/B17)*100 -> #DIV/0! | L17: =E17/$B17*100 -> #DIV/0! | M17: =F17/$B17*100 -> #DIV/0! | N17: =G17/$B17*100 -> #DIV/0! | O17: =H17/$B17*100 -> #DIV/0! | P17: =I17/$B17*100 -> #DIV/0! | R17: =(D17/D13-1)*100 -> #DIV/0! | S17: =(E17/E13-1)*100 -> #DIV/0! | T17: =(F17/F13-1)*100 -> #DIV/0! | U17: =(G17/G13-1)*100 -> #DIV/0! | V17: =(H17/H13-1)*100 -> #DIV/0! | W17: =(I17/I13-1)*100 -> #DIV/0! | Y17: =(B17/B13-1)*100 -> #DIV/0! | Z17: =((D17-D13)/$B13)*100 -> #DIV/0! | AA17: =((E17-E13)/$B13)*100 -> #DIV/0! | AB17: =((F17-F13)/$B13)*100 -> #DIV/0! | AC17: =((G17-G13)/$B13)*100 -> #DIV/0! | AD17: =((H17-H13)/$B13)*100 -> #DIV/0! | AE17: =((I17-I13)/$B13)*100 -> #DIV/0!
A18: Q3-1994 | B18: ='1.Reel GSYH '!B15 -> 0 | D18: ='1.Reel GSYH '!D15 -> 0 | E18: ='1.Reel GSYH '!E15 -> 0 | F18: ='1.Reel GSYH '!F15 -> 0 | G18: ='1.Reel GSYH '!G15 -> 0 | H18: ='1.Reel GSYH '!H15 -> 0 | I18: ='1.Reel GSYH '!I15 -> 0 | K18: =(D18/B18)*100 -> #DIV/0! | L18: =E18/$B18*100 -> #DIV/0! | M18: =F18/$B18*100 -> #DIV/0! | N18: =G18/$B18*100 -> #DIV/0! | O18: =H18/$B18*100 -> #DIV/0! | P18: =I18/$B18*100 -> #DIV/0! | R18: =(D18/D14-1)*100 -> #DIV/0! | S18: =(E18/E14-1)*100 -> #DIV/0! | T18: =(F18/F14-1)*100 -> #DIV/0! | U18: =(G18/G14-1)*100 -> #DIV/0! | V18: =(H18/H14-1)*100 -> #DIV/0! | W18: =(I18/I14-1)*100 -> #DIV/0! | Y18: =(B18/B14-1)*100 -> #DIV/0! | Z18: =((D18-D14)/$B14)*100 -> #DIV/0! | AA18: =((E18-E14)/$B14)*100 -> #DIV/0! | AB18: =((F18-F14)/$B14)*100 -> #DIV/0! | AC18: =((G18-G14)/$B14)*100 -> #DIV/0! | AD18: =((H18-H14)/$B14)*100 -> #DIV/0! | AE18: =((I18-I14)/$B14)*100 -> #DIV/0!
A19: Q4-1994 | B19: ='1.Reel GSYH '!B16 -> 0 | D19: ='1.Reel GSYH '!D16 -> 0 | E19: ='1.Reel GSYH '!E16 -> 0 | F19: ='1.Reel GSYH '!F16 -> 0 | G19: ='1.Reel GSYH '!G16 -> 0 | H19: ='1.Reel GSYH '!H16 -> 0 | I19: ='1.Reel GSYH '!I16 -> 0 | K19: =(D19/B19)*100 -> #DIV/0! | L19: =E19/$B19*100 -> #DIV/0! | M19: =F19/$B19*100 -> #DIV/0! | N19: =G19/$B19*100 -> #DIV/0! | O19: =H19/$B19*100 -> #DIV/0! | P19: =I19/$B19*100 -> #DIV/0! | R19: =(D19/D15-1)*100 -> #DIV/0! | S19: =(E19/E15-1)*100 -> #DIV/0! | T19: =(F19/F15-1)*100 -> #DIV/0! | U19: =(G19/G15-1)*100 -> #DIV/0! | V19: =(H19/H15-1)*100 -> #DIV/0! | W19: =(I19/I15-1)*100 -> #DIV/0! | Y19: =(B19/B15-1)*100 -> #DIV/0! | Z19: =((D19-D15)/$B15)*100 -> #DIV/0! | AA19: =((E19-E15)/$B15)*100 -> #DIV/0! | AB19: =((F19-F15)/$B15)*100 -> #DIV/0! | AC19: =((G19-G15)/$B15)*100 -> #DIV/0! | AD19: =((H19-H15)/$B15)*100 -> #DIV/0! | AE19: =((I19-I15)/$B15)*100 -> #DIV/0!
A20: Q1-1995 | B20: ='1.Reel GSYH '!B17 -> 0 | D20: ='1.Reel GSYH '!D17 -> 0 | E20: ='1.Reel GSYH '!E17 -> 0 | F20: ='1.Reel GSYH '!F17 -> 0 | G20: ='1.Reel GSYH '!G17 -> 0 | H20: ='1.Reel GSYH '!H17 -> 0 | I20: ='1.Reel GSYH '!I17 -> 0 | K20: =(D20/B20)*100 -> #DIV/0! | L20: =E20/$B20*100 -> #DIV/0! | M20: =F20/$B20*100 -> #DIV/0! | N20: =G20/$B20*100 -> #DIV/0! | O20: =H20/$B20*100 -> #DIV/0! | P20: =I20/$B20*100 -> #DIV/0! | R20: =(D20/D16-1)*100 -> #DIV/0! | S20: =(E20/E16-1)*100 -> #DIV/0! | T20: =(F20/F16-1)*100 -> #DIV/0! | U20: =(G20/G16-1)*100 -> #DIV/0! | V20: =(H20/H16-1)*100 -> #DIV/0! | W20: =(I20/I16-1)*100 -> #DIV/0! | Y20: =(B20/B16-1)*100 -> #DIV/0! | Z20: =((D20-D16)/$B16)*100 -> #DIV/0! | AA20: =((E20-E16)/$B16)*100 -> #DIV/0! | AB20: =((F20-F16)/$B16)*100 -> #DIV/0! | AC20: =((G20-G16)/$B16)*100 -> #DIV/0! | AD20: =((H20-H16)/$B16)*100 -> #DIV/0! | AE20: =((I20-I16)/$B16)*100 -> #DIV/0!
A21: Q2-1995 | B21: ='1.Reel GSYH '!B18 -> 0 | D21: ='1.Reel GSYH '!D18 -> 0 | E21: ='1.Reel GSYH '!E18 -> 0 | F21: ='1.Reel GSYH '!F18 -> 0 | G21: ='1.Reel GSYH '!G18 -> 0 | H21: ='1.Reel GSYH '!H18 -> 0 | I21: ='1.Reel GSYH '!I18 -> 0 | K21: =(D21/B21)*100 -> #DIV/0! | L21: =E21/$B21*100 -> #DIV/0! | M21: =F21/$B21*100 -> #DIV/0! | N21: =G21/$B21*100 -> #DIV/0! | O21: =H21/$B21*100 -> #DIV/0! | P21: =I21/$B21*100 -> #DIV/0! | R21: =(D21/D17-1)*100 -> #DIV/0! | S21: =(E21/E17-1)*100 -> #DIV/0! | T21: =(F21/F17-1)*100 -> #DIV/0! | U21: =(G21/G17-1)*100 -> #DIV/0! | V21: =(H21/H17-1)*100 -> #DIV/0! | W21: =(I21/I17-1)*100 -> #DIV/0! | Y21: =(B21/B17-1)*100 -> #DIV/0! | Z21: =((D21-D17)/$B17)*100 -> #DIV/0! | AA21: =((E21-E17)/$B17)*100 -> #DIV/0! | AB21: =((F21-F17)/$B17)*100 -> #DIV/0! | AC21: =((G21-G17)/$B17)*100 -> #DIV/0! | AD21: =((H21-H17)/$B17)*100 -> #DIV/0! | AE21: =((I21-I17)/$B17)*100 -> #DIV/0!
A22: Q3-1995 | B22: ='1.Reel GSYH '!B19 -> 0 | D22: ='1.Reel GSYH '!D19 -> 0 | E22: ='1.Reel GSYH '!E19 -> 0 | F22: ='1.Reel GSYH '!F19 -> 0 | G22: ='1.Reel GSYH '!G19 -> 0 | H22: ='1.Reel GSYH '!H19 -> 0 | I22: ='1.Reel GSYH '!I19 -> 0 | K22: =(D22/B22)*100 -> #DIV/0! | L22: =E22/$B22*100 -> #DIV/0! | M22: =F22/$B22*100 -> #DIV/0! | N22: =G22/$B22*100 -> #DIV/0! | O22: =H22/$B22*100 -> #DIV/0! | P22: =I22/$B22*100 -> #DIV/0! | R22: =(D22/D18-1)*100 -> #DIV/0! | S22: =(E22/E18-1)*100 -> #DIV/0! | T22: =(F22/F18-1)*100 -> #DIV/0! | U22: =(G22/G18-1)*100 -> #DIV/0! | V22: =(H22/H18-1)*100 -> #DIV/0! | W22: =(I22/I18-1)*100 -> #DIV/0! | Y22: =(B22/B18-1)*100 -> #DIV/0! | Z22: =((D22-D18)/$B18)*100 -> #DIV/0! | AA22: =((E22-E18)/$B18)*100 -> #DIV/0! | AB22: =((F22-F18)/$B18)*100 -> #DIV/0! | AC22: =((G22-G18)/$B18)*100 -> #DIV/0! | AD22: =((H22-H18)/$B18)*100 -> #DIV/0! | AE22: =((I22-I18)/$B18)*100 -> #DIV/0!
A23: Q4-1995 | B23: ='1.Reel GSYH '!B20 -> 0 | D23: ='1.Reel GSYH '!D20 -> 0 | E23: ='1.Reel GSYH '!E20 -> 0 | F23: ='1.Reel GSYH '!F20 -> 0 | G23: ='1.Reel GSYH '!G20 -> 0 | H23: ='1.Reel GSYH '!H20 -> 0 | I23: ='1.Reel GSYH '!I20 -> 0 | K23: =(D23/B23)*100 -> #DIV/0! | L23: =E23/$B23*100 -> #DIV/0! | M23: =F23/$B23*100 -> #DIV/0! | N23: =G23/$B23*100 -> #DIV/0! | O23: =H23/$B23*100 -> #DIV/0! | P23: =I23/$B23*100 -> #DIV/0! | R23: =(D23/D19-1)*100 -> #DIV/0! | S23: =(E23/E19-1)*100 -> #DIV/0! | T23: =(F23/F19-1)*100 -> #DIV/0! | U23: =(G23/G19-1)*100 -> #DIV/0! | V23: =(H23/H19-1)*100 -> #DIV/0! | W23: =(I23/I19-1)*100 -> #DIV/0! | Y23: =(B23/B19-1)*100 -> #DIV/0! | Z23: =((D23-D19)/$B19)*100 -> #DIV/0! | AA23: =((E23-E19)/$B19)*100 -> #DIV/0! | AB23: =((F23-F19)/$B19)*100 -> #DIV/0! | AC23: =((G23-G19)/$B19)*100 -> #DIV/0! | AD23: =((H23-H19)/$B19)*100 -> #DIV/0! | AE23: =((I23-I19)/$B19)*100 -> #DIV/0!
A24: Q1-1996 | B24: ='1.Reel GSYH '!B21 -> 0 | D24: ='1.Reel GSYH '!D21 -> 0 | E24: ='1.Reel GSYH '!E21 -> 0 | F24: ='1.Reel GSYH '!F21 -> 0 | G24: ='1.Reel GSYH '!G21 -> 0 | H24: ='1.Reel GSYH '!H21 -> 0 | I24: ='1.Reel GSYH '!I21 -> 0 | K24: =(D24/B24)*100 -> #DIV/0! | L24: =E24/$B24*100 -> #DIV/0! | M24: =F24/$B24*100 -> #DIV/0! | N24: =G24/$B24*100 -> #DIV/0! | O24: =H24/$B24*100 -> #DIV/0! | P24: =I24/$B24*100 -> #DIV/0! | R24: =(D24/D20-1)*100 -> #DIV/0! | S24: =(E24/E20-1)*100 -> #DIV/0! | T24: =(F24/F20-1)*100 -> #DIV/0! | U24: =(G24/G20-1)*100 -> #DIV/0! | V24: =(H24/H20-1)*100 -> #DIV/0! | W24: =(I24/I20-1)*100 -> #DIV/0! | Y24: =(B24/B20-1)*100 -> #DIV/0! | Z24: =((D24-D20)/$B20)*100 -> #DIV/0! | AA24: =((E24-E20)/$B20)*100 -> #DIV/0! | AB24: =((F24-F20)/$B20)*100 -> #DIV/0! | AC24: =((G24-G20)/$B20)*100 -> #DIV/0! | AD24: =((H24-H20)/$B20)*100 -> #DIV/0! | AE24: =((I24-I20)/$B20)*100 -> #DIV/0!
A25: Q2-1996 | B25: ='1.Reel GSYH '!B22 -> 0 | D25: ='1.Reel GSYH '!D22 -> 0 | E25: ='1.Reel GSYH '!E22 -> 0 | F25: ='1.Reel GSYH '!F22 -> 0 | G25: ='1.Reel GSYH '!G22 -> 0 | H25: ='1.Reel GSYH '!H22 -> 0 | I25: ='1.Reel GSYH '!I22 -> 0 | K25: =(D25/B25)*100 -> #DIV/0! | L25: =E25/$B25*100 -> #DIV/0! | M25: =F25/$B25*100 -> #DIV/0! | N25: =G25/$B25*100 -> #DIV/0! | O25: =H25/$B25*100 -> #DIV/0! | P25: =I25/$B25*100 -> #DIV/0! | R25: =(D25/D21-1)*100 -> #DIV/0! | S25: =(E25/E21-1)*100 -> #DIV/0! | T25: =(F25/F21-1)*100 -> #DIV/0! | U25: =(G25/G21-1)*100 -> #DIV/0! | V25: =(H25/H21-1)*100 -> #DIV/0! | W25: =(I25/I21-1)*100 -> #DIV/0! | Y25: =(B25/B21-1)*100 -> #DIV/0! | Z25: =((D25-D21)/$B21)*100 -> #DIV/0! | AA25: =((E25-E21)/$B21)*100 -> #DIV/0! | AB25: =((F25-F21)/$B21)*100 -> #DIV/0! | AC25: =((G25-G21)/$B21)*100 -> #DIV/0! | AD25: =((H25-H21)/$B21)*100 -> #DIV/0! | AE25: =((I25-I21)/$B21)*100 -> #DIV/0!
A26: Q3-1996 | B26: ='1.Reel GSYH '!B23 -> 0 | D26: ='1.Reel GSYH '!D23 -> 0 | E26: ='1.Reel GSYH '!E23 -> 0 | F26: ='1.Reel GSYH '!F23 -> 0 | G26: ='1.Reel GSYH '!G23 -> 0 | H26: ='1.Reel GSYH '!H23 -> 0 | I26: ='1.Reel GSYH '!I23 -> 0 | K26: =(D26/B26)*100 -> #DIV/0! | L26: =E26/$B26*100 -> #DIV/0! | M26: =F26/$B26*100 -> #DIV/0! | N26: =G26/$B26*100 -> #DIV/0! | O26: =H26/$B26*100 -> #DIV/0! | P26: =I26/$B26*100 -> #DIV/0! | R26: =(D26/D22-1)*100 -> #DIV/0! | S26: =(E26/E22-1)*100 -> #DIV/0! | T26: =(F26/F22-1)*100 -> #DIV/0! | U26: =(G26/G22-1)*100 -> #DIV/0! | V26: =(H26/H22-1)*100 -> #DIV/0! | W26: =(I26/I22-1)*100 -> #DIV/0! | Y26: =(B26/B22-1)*100 -> #DIV/0! | Z26: =((D26-D22)/$B22)*100 -> #DIV/0! | AA26: =((E26-E22)/$B22)*100 -> #DIV/0! | AB26: =((F26-F22)/$B22)*100 -> #DIV/0! | AC26: =((G26-G22)/$B22)*100 -> #DIV/0! | AD26: =((H26-H22)/$B22)*100 -> #DIV/0! | AE26: =((I26-I22)/$B22)*100 -> #DIV/0!
A27: Q4-1996 | B27: ='1.Reel GSYH '!B24 -> 0 | D27: ='1.Reel GSYH '!D24 -> 0 | E27: ='1.Reel GSYH '!E24 -> 0 | F27: ='1.Reel GSYH '!F24 -> 0 | G27: ='1.Reel GSYH '!G24 -> 0 | H27: ='1.Reel GSYH '!H24 -> 0 | I27: ='1.Reel GSYH '!I24 -> 0 | K27: =(D27/B27)*100 -> #DIV/0! | L27: =E27/$B27*100 -> #DIV/0! | M27: =F27/$B27*100 -> #DIV/0! | N27: =G27/$B27*100 -> #DIV/0! | O27: =H27/$B27*100 -> #DIV/0! | P27: =I27/$B27*100 -> #DIV/0! | R27: =(D27/D23-1)*100 -> #DIV/0! | S27: =(E27/E23-1)*100 -> #DIV/0! | T27: =(F27/F23-1)*100 -> #DIV/0! | U27: =(G27/G23-1)*100 -> #DIV/0! | V27: =(H27/H23-1)*100 -> #DIV/0! | W27: =(I27/I23-1)*100 -> #DIV/0! | Y27: =(B27/B23-1)*100 -> #DIV/0! | Z27: =((D27-D23)/$B23)*100 -> #DIV/0! | AA27: =((E27-E23)/$B23)*100 -> #DIV/0! | AB27: =((F27-F23)/$B23)*100 -> #DIV/0! | AC27: =((G27-G23)/$B23)*100 -> #DIV/0! | AD27: =((H27-H23)/$B23)*100 -> #DIV/0! | AE27: =((I27-I23)/$B23)*100 -> #DIV/0!
... A31: Q4-1997 | B31: ='1.Reel GSYH '!B28 -> 0 | D31: ='1.Reel GSYH '!D28 -> 0 | E31: ='1.Reel GSYH '!E28 -> 0 | F31: ='1.Reel GSYH '!F28 -> 0 | G31: ='1.Reel GSYH '!G28 -> 0 | H31: ='1.Reel GSYH '!H28 -> 0 | I31: ='1.Reel GSYH '!I28 -> 0 | K31: =(D31/B31)*100 -> #DIV/0! | L31: =E31/$B31*100 -> #DIV/0! | M31: =F31/$B31*100 -> #DIV/0! | N31: =G31/$B31*100 -> #DIV/0! | O31: =H31/$B31*100 -> #DIV/0! | P31: =I31/$B31*100 -> #DIV/0! | R31: =(D31/D27-1)*100 -> #DIV/0! | S31: =(E31/E27-1)*100 -> #DIV/0! | T31: =(F31/F27-1)*100 -> #DIV/0! | U31: =(G31/G27-1)*100 -> #DIV/0! | V31: =(H31/H27-1)*100 -> #DIV/0! | W31: =(I31/I27-1)*100 -> #DIV/0! | Y31: =(B31/B27-1)*100 -> #DIV/0! | Z31: =((D31-D27)/$B27)*100 -> #DIV/0! | AA31: =((E31-E27)/$B27)*100 -> #DIV/0! | AB31: =((F31-F27)/$B27)*100 -> #DIV/0! | AC31: =((G31-G27)/$B27)*100 -> #DIV/0! | AD31: =((H31-H27)/$B27)*100 -> #DIV/0! | AE31: =((I31-I27)/$B27)*100 -> #DIV/0!
A32: Q1-1998 | B32: 192563.4 | D32: ='1.Reel GSYH '!D29 -> 0 | E32: ='1.Reel GSYH '!E29 -> 0 | F32: ='1.Reel GSYH '!F29 -> 0 | G32: ='1.Reel GSYH '!G29 -> 0 | H32: ='1.Reel GSYH '!H29 -> 0 | I32: ='1.Reel GSYH '!I29 -> 0 | K32: =(D32/B32)*100 -> 0 | L32: =E32/$B32*100 -> 0 | M32: =F32/$B32*100 -> 0 | N32: =G32/$B32*100 -> 0 | O32: =H32/$B32*100 -> 0 | P32: =I32/$B32*100 -> 0 | R32: =(D32/D28-1)*100 -> #DIV/0! | S32: =(E32/E28-1)*100 -> #DIV/0! | T32: =(F32/F28-1)*100 -> #DIV/0! | U32: =(G32/G28-1)*100 -> #DIV/0! | V32: =(H32/H28-1)*100 -> #DIV/0! | W32: =(I32/I28-1)*100 -> #DIV/0! | Y32: =(B32/B28-1)*100 -> #DIV/0! | Z32: =((D32-D28)/$B28)*100 -> #DIV/0! | AA32: =((E32-E28)/$B28)*100 -> #DIV/0! | AB32: =((F32-F28)/$B28)*100 -> #DIV/0! | AC32: =((G32-G28)/$B28)*100 -> #DIV/0! | AD32: =((H32-H28)/$B28)*100 -> #DIV/0! | AE32: =((I32-I28)/$B28)*100 -> #DIV/0!
A33: Q2-1998 | B33: 191029.55 | D33: ='1.Reel GSYH '!D30 -> 0 | E33: ='1.Reel GSYH '!E30 -> 0 | F33: ='1.Reel GSYH '!F30 -> 0 | G33: ='1.Reel GSYH '!G30 -> 0 | H33: ='1.Reel GSYH '!H30 -> 0 | I33: ='1.Reel GSYH '!I30 -> 0 | K33: =(D33/B33)*100 -> 0 | L33: =E33/$B33*100 -> 0 | M33: =F33/$B33*100 -> 0 | N33: =G33/$B33*100 -> 0 | O33: =H33/$B33*100 -> 0 | P33: =I33/$B33*100 -> 0 | R33: =(D33/D29-1)*100 -> #DIV/0! | S33: =(E33/E29-1)*100 -> #DIV/0! | T33: =(F33/F29-1)*100 -> #DIV/0! | U33: =(G33/G29-1)*100 -> #DIV/0! | V33: =(H33/H29-1)*100 -> #DIV/0! | W33: =(I33/I29-1)*100 -> #DIV/0! | Y33: =(B33/B29-1)*100 -> #DIV/0! | Z33: =((D33-D29)/$B29)*100 -> #DIV/0! | AA33: =((E33-E29)/$B29)*100 -> #DIV/0! | AB33: =((F33-F29)/$B29)*100 -> #DIV/0! | AC33: =((G33-G29)/$B29)*100 -> #DIV/0! | AD33: =((H33-H29)/$B29)*100 -> #DIV/0! | AE33: =((I33-I29)/$B29)*100 -> #DIV/0!
A34: Q3-1998 | B34: 188341.62 | D34: ='1.Reel GSYH '!D31 -> 0 | E34: ='1.Reel GSYH '!E31 -> 0 | F34: ='1.Reel GSYH '!F31 -> 0 | G34: ='1.Reel GSYH '!G31 -> 0 | H34: ='1.Reel GSYH '!H31 -> 0 | I34: ='1.Reel GSYH '!I31 -> 0 | K34: =(D34/B34)*100 -> 0 | L34: =E34/$B34*100 -> 0 | M34: =F34/$B34*100 -> 0 | N34: =G34/$B34*100 -> 0 | O34: =H34/$B34*100 -> 0 | P34: =I34/$B34*100 -> 0 | R34: =(D34/D30-1)*100 -> #DIV/0! | S34: =(E34/E30-1)*100 -> #DIV/0! | T34: =(F34/F30-1)*100 -> #DIV/0! | U34: =(G34/G30-1)*100 -> #DIV/0! | V34: =(H34/H30-1)*100 -> #DIV/0! | W34: =(I34/I30-1)*100 -> #DIV/0! | Y34: =(B34/B30-1)*100 -> #DIV/0! | Z34: =((D34-D30)/$B30)*100 -> #DIV/0! | AA34: =((E34-E30)/$B30)*100 -> #DIV/0! | AB34: =((F34-F30)/$B30)*100 -> #DIV/0! | AC34: =((G34-G30)/$B30)*100 -> #DIV/0! | AD34: =((H34-H30)/$B30)*100 -> #DIV/0! | AE34: =((I34-I30)/$B30)*100 -> #DIV/0!
A35: Q4-1998 | B35: 187854.4 | D35: ='1.Reel GSYH '!D32 -> 0 | E35: ='1.Reel GSYH '!E32 -> 0 | F35: ='1.Reel GSYH '!F32 -> 0 | G35: ='1.Reel GSYH '!G32 -> 0 | H35: ='1.Reel GSYH '!H32 -> 0 | I35: ='1.Reel GSYH '!I32 -> 0 | K35: =(D35/B35)*100 -> 0 | L35: =E35/$B35*100 -> 0 | M35: =F35/$B35*100 -> 0 | N35: =G35/$B35*100 -> 0 | O35: =H35/$B35*100 -> 0 | P35: =I35/$B35*100 -> 0 | R35: =(D35/D31-1)*100 -> #DIV/0! | S35: =(E35/E31-1)*100 -> #DIV/0! | T35: =(F35/F31-1)*100 -> #DIV/0! | U35: =(G35/G31-1)*100 -> #DIV/0! | V35: =(H35/H31-1)*100 -> #DIV/0! | W35: =(I35/I31-1)*100 -> #DIV/0! | Y35: =(B35/B31-1)*100 -> #DIV/0! | Z35: =((D35-D31)/$B31)*100 -> #DIV/0! | AA35: =((E35-E31)/$B31)*100 -> #DIV/0! | AB35: =((F35-F31)/$B31)*100 -> #DIV/0! | AC35: =((G35-G31)/$B31)*100 -> #DIV/0! | AD35: =((H35-H31)/$B31)*100 -> #DIV/0! | AE35: =((I35-I31)/$B31)*100 -> #DIV/0!
A36: Q1-1999 | B36: 184687.51 | D36: ='1.Reel GSYH '!D33 -> 0 | E36: ='1.Reel GSYH '!E33 -> 0 | F36: ='1.Reel GSYH '!F33 -> 0 | G36: ='1.Reel GSYH '!G33 -> 0 | H36: ='1.Reel GSYH '!H33 -> 0 | I36: ='1.Reel GSYH '!I33 -> 0 | K36: =(D36/B36)*100 -> 0 | L36: =E36/$B36*100 -> 0 | M36: =F36/$B36*100 -> 0 | N36: =G36/$B36*100 -> 0 | O36: =H36/$B36*100 -> 0 | P36: =I36/$B36*100 -> 0 | R36: =(D36/D32-1)*100 -> #DIV/0! | S36: =(E36/E32-1)*100 -> #DIV/0! | T36: =(F36/F32-1)*100 -> #DIV/0! | U36: =(G36/G32-1)*100 -> #DIV/0! | V36: =(H36/H32-1)*100 -> #DIV/0! | W36: =(I36/I32-1)*100 -> #DIV/0! | Y36: =(B36/B32-1)*100 -> -4.0900213 | Z36: =((D36-D32)/$B32)*100 -> 0 | AA36: =((E36-E32)/$B32)*100 -> 0 | AB36: =((F36-F32)/$B32)*100 -> 0 | AC36: =((G36-G32)/$B32)*100 -> 0 | AD36: =((H36-H32)/$B32)*100 -> 0 | AE36: =((I36-I32)/$B32)*100 -> 0
A37: Q2-1999 | B37: 183646.4 | D37: ='1.Reel GSYH '!D34 -> 0 | E37: ='1.Reel GSYH '!E34 -> 0 | F37: ='1.Reel GSYH '!F34 -> 0 | G37: ='1.Reel GSYH '!G34 -> 0 | H37: ='1.Reel GSYH '!H34 -> 0 | I37: ='1.Reel GSYH '!I34 -> 0 | K37: =(D37/B37)*100 -> 0 | L37: =E37/$B37*100 -> 0 | M37: =F37/$B37*100 -> 0 | N37: =G37/$B37*100 -> 0 | O37: =H37/$B37*100 -> 0 | P37: =I37/$B37*100 -> 0 | R37: =(D37/D33-1)*100 -> #DIV/0! | S37: =(E37/E33-1)*100 -> #DIV/0! | T37: =(F37/F33-1)*100 -> #DIV/0! | U37: =(G37/G33-1)*100 -> #DIV/0! | V37: =(H37/H33-1)*100 -> #DIV/0! | W37: =(I37/I33-1)*100 -> #DIV/0! | Y37: =(B37/B33-1)*100 -> -3.8649237 | Z37: =((D37-D33)/$B33)*100 -> 0 | AA37: =((E37-E33)/$B33)*100 -> 0 | AB37: =((F37-F33)/$B33)*100 -> 0 | AC37: =((G37-G33)/$B33)*100 -> 0 | AD37: =((H37-H33)/$B33)*100 -> 0 | AE37: =((I37-I33)/$B33)*100 -> 0
A38: Q3-1999 | B38: 180548.99 | D38: ='1.Reel GSYH '!D35 -> 0 | E38: ='1.Reel GSYH '!E35 -> 0 | F38: ='1.Reel GSYH '!F35 -> 0 | G38: ='1.Reel GSYH '!G35 -> 0 | H38: ='1.Reel GSYH '!H35 -> 0 | I38: ='1.Reel GSYH '!I35 -> 0 | K38: =(D38/B38)*100 -> 0 | L38: =E38/$B38*100 -> 0 | M38: =F38/$B38*100 -> 0 | N38: =G38/$B38*100 -> 0 | O38: =H38/$B38*100 -> 0 | P38: =I38/$B38*100 -> 0 | R38: =(D38/D34-1)*100 -> #DIV/0! | S38: =(E38/E34-1)*100 -> #DIV/0! | T38: =(F38/F34-1)*100 -> #DIV/0! | U38: =(G38/G34-1)*100 -> #DIV/0! | V38: =(H38/H34-1)*100 -> #DIV/0! | W38: =(I38/I34-1)*100 -> #DIV/0! | Y38: =(B38/B34-1)*100 -> -4.137498 | Z38: =((D38-D34)/$B34)*100 -> 0 | AA38: =((E38-E34)/$B34)*100 -> 0 | AB38: =((F38-F34)/$B34)*100 -> 0 | AC38: =((G38-G34)/$B34)*100 -> 0 | AD38: =((H38-H34)/$B34)*100 -> 0 | AE38: =((I38-I34)/$B34)*100 -> 0
A39: Q4-1999 | B39: 185942.75 | D39: ='1.Reel GSYH '!D36 -> 0 | E39: ='1.Reel GSYH '!E36 -> 0 | F39: ='1.Reel GSYH '!F36 -> 0 | G39: ='1.Reel GSYH '!G36 -> 0 | H39: ='1.Reel GSYH '!H36 -> 0 | I39: ='1.Reel GSYH '!I36 -> 0 | K39: =(D39/B39)*100 -> 0 | L39: =E39/$B39*100 -> 0 | M39: =F39/$B39*100 -> 0 | N39: =G39/$B39*100 -> 0 | O39: =H39/$B39*100 -> 0 | P39: =I39/$B39*100 -> 0 | R39: =(D39/D35-1)*100 -> #DIV/0! | S39: =(E39/E35-1)*100 -> #DIV/0! | T39: =(F39/F35-1)*100 -> #DIV/0! | U39: =(G39/G35-1)*100 -> #DIV/0! | V39: =(H39/H35-1)*100 -> #DIV/0! | W39: =(I39/I35-1)*100 -> #DIV/0! | Y39: =(B39/B35-1)*100 -> -1.0176265 | Z39: =((D39-D35)/$B35)*100 -> 0 | AA39: =((E39-E35)/$B35)*100 -> 0 | AB39: =((F39-F35)/$B35)*100 -> 0 | AC39: =((G39-G35)/$B35)*100 -> 0 | AD39: =((H39-H35)/$B35)*100 -> 0 | AE39: =((I39-I35)/$B35)*100 -> 0
A40: Q1-2000 | B40: 188871.07 | D40: ='1.Reel GSYH '!D37 -> 0 | E40: ='1.Reel GSYH '!E37 -> 0 | F40: ='1.Reel GSYH '!F37 -> 0 | G40: ='1.Reel GSYH '!G37 -> 0 | H40: ='1.Reel GSYH '!H37 -> 0 | I40: ='1.Reel GSYH '!I37 -> 0 | K40: =(D40/B40)*100 -> 0 | L40: =E40/$B40*100 -> 0 | M40: =F40/$B40*100 -> 0 | N40: =G40/$B40*100 -> 0 | O40: =H40/$B40*100 -> 0 | P40: =I40/$B40*100 -> 0 | R40: =(D40/D36-1)*100 -> #DIV/0! | S40: =(E40/E36-1)*100 -> #DIV/0! | T40: =(F40/F36-1)*100 -> #DIV/0! | U40: =(G40/G36-1)*100 -> #DIV/0! | V40: =(H40/H36-1)*100 -> #DIV/0! | W40: =(I40/I36-1)*100 -> #DIV/0! | Y40: =(B40/B36-1)*100 -> 2.2652063 | Z40: =((D40-D36)/$B36)*100 -> 0 | AA40: =((E40-E36)/$B36)*100 -> 0 | AB40: =((F40-F36)/$B36)*100 -> 0 | AC40: =((G40-G36)/$B36)*100 -> 0 | AD40: =((H40-H36)/$B36)*100 -> 0 | AE40: =((I40-I36)/$B36)*100 -> 0
A41: Q2-2000 | B41: 196224.52 | D41: ='1.Reel GSYH '!D38 -> 0 | E41: ='1.Reel GSYH '!E38 -> 0 | F41: ='1.Reel GSYH '!F38 -> 0 | G41: ='1.Reel GSYH '!G38 -> 0 | H41: ='1.Reel GSYH '!H38 -> 0 | I41: ='1.Reel GSYH '!I38 -> 0 | K41: =(D41/B41)*100 -> 0 | L41: =E41/$B41*100 -> 0 | M41: =F41/$B41*100 -> 0 | N41: =G41/$B41*100 -> 0 | O41: =H41/$B41*100 -> 0 | P41: =I41/$B41*100 -> 0 | R41: =(D41/D37-1)*100 -> #DIV/0! | S41: =(E41/E37-1)*100 -> #DIV/0! | T41: =(F41/F37-1)*100 -> #DIV/0! | U41: =(G41/G37-1)*100 -> #DIV/0! | V41: =(H41/H37-1)*100 -> #DIV/0! | W41: =(I41/I37-1)*100 -> #DIV/0! | Y41: =(B41/B37-1)*100 -> 6.8490946 | Z41: =((D41-D37)/$B37)*100 -> 0 | AA41: =((E41-E37)/$B37)*100 -> 0 | AB41: =((F41-F37)/$B37)*100 -> 0 | AC41: =((G41-G37)/$B37)*100 -> 0 | AD41: =((H41-H37)/$B37)*100 -> 0 | AE41: =((I41-I37)/$B37)*100 -> 0
A42: Q3-2000 | B42: 199146.92 | D42: ='1.Reel GSYH '!D39 -> 0 | E42: ='1.Reel GSYH '!E39 -> 0 | F42: ='1.Reel GSYH '!F39 -> 0 | G42: ='1.Reel GSYH '!G39 -> 0 | H42: ='1.Reel GSYH '!H39 -> 0 | I42: ='1.Reel GSYH '!I39 -> 0 | K42: =(D42/B42)*100 -> 0 | L42: =E42/$B42*100 -> 0 | M42: =F42/$B42*100 -> 0 | N42: =G42/$B42*100 -> 0 | O42: =H42/$B42*100 -> 0 | P42: =I42/$B42*100 -> 0 | R42: =(D42/D38-1)*100 -> #DIV/0! | S42: =(E42/E38-1)*100 -> #DIV/0! | T42: =(F42/F38-1)*100 -> #DIV/0! | U42: =(G42/G38-1)*100 -> #DIV/0! | V42: =(H42/H38-1)*100 -> #DIV/0! | W42: =(I42/I38-1)*100 -> #DIV/0! | Y42: =(B42/B38-1)*100 -> 10.300768 | Z42: =((D42-D38)/$B38)*100 -> 0 | AA42: =((E42-E38)/$B38)*100 -> 0 | AB42: =((F42-F38)/$B38)*100 -> 0 | AC42: =((G42-G38)/$B38)*100 -> 0 | AD42: =((H42-H38)/$B38)*100 -> 0 | AE42: =((I42-I38)/$B38)*100 -> 0
A43: Q4-2000 | B43: 202007.93 | D43: ='1.Reel GSYH '!D40 -> 0 | E43: ='1.Reel GSYH '!E40 -> 0 | F43: ='1.Reel GSYH '!F40 -> 0 | G43: ='1.Reel GSYH '!G40 -> 0 | H43: ='1.Reel GSYH '!H40 -> 0 | I43: ='1.Reel GSYH '!I40 -> 0 | K43: =(D43/B43)*100 -> 0 | L43: =E43/$B43*100 -> 0 | M43: =F43/$B43*100 -> 0 | N43: =G43/$B43*100 -> 0 | O43: =H43/$B43*100 -> 0 | P43: =I43/$B43*100 -> 0 | R43: =(D43/D39-1)*100 -> #DIV/0! | S43: =(E43/E39-1)*100 -> #DIV/0! | T43: =(F43/F39-1)*100 -> #DIV/0! | U43: =(G43/G39-1)*100 -> #DIV/0! | V43: =(H43/H39-1)*100 -> #DIV/0! | W43: =(I43/I39-1)*100 -> #DIV/0! | Y43: =(B43/B39-1)*100 -> 8.6398569 | Z43: =((D43-D39)/$B39)*100 -> 0 | AA43: =((E43-E39)/$B39)*100 -> 0 | AB43: =((F43-F39)/$B39)*100 -> 0 | AC43: =((G43-G39)/$B39)*100 -> 0 | AD43: =((H43-H39)/$B39)*100 -> 0 | AE43: =((I43-I39)/$B39)*100 -> 0
... A106: Q3-2016 | B106: 413311.19 | D106: ='1.Reel GSYH '!D103 -> 633640.3 | E106: ='1.Reel GSYH '!E103 -> 23443 | F106: ='1.Reel GSYH '!F103 -> 25604.2 | G106: ='1.Reel GSYH '!G103 -> 90550.4 | H106: ='1.Reel GSYH '!H103 -> 114067 | I106: ='1.Reel GSYH '!I103 -> 379975.7 | K106: =(D106/B106)*100 -> 153.30829 | L106: =E106/$B106*100 -> 5.6719974 | M106: =F106/$B106*100 -> 6.1948964 | N106: =G106/$B106*100 -> 21.908528 | O106: =H106/$B106*100 -> 27.598333 | P106: =I106/$B106*100 -> 91.93453 | R106: =(D106/D102-1)*100 -> 2.3470154 | S106: =(E106/E102-1)*100 -> -12.895986 | T106: =(F106/F102-1)*100 -> 4.6034301 | U106: =(G106/G102-1)*100 -> 0.3958161 | V106: =(H106/H102-1)*100 -> -2.1450251 | W106: =(I106/I102-1)*100 -> 5.2687614 | Y106: =(B106/B102-1)*100 -> 0.032153892 | Z106: =((D106-D102)/$B102)*100 -> 3.5167865 | AA106: =((E106-E102)/$B102)*100 -> -0.84002468 | AB106: =((F106-F102)/$B102)*100 -> 0.27271517 | AC106: =((G106-G102)/$B102)*100 -> 0.086403368 | AD106: =((H106-H102)/$B102)*100 -> -0.60516241 | AE106: =((I106-I102)/$B102)*100 -> 4.6028551
A109: 1993-1997 | B109: =AVERAGE(B12:B31) -> 0 | D109: =AVERAGE(D12:D31) -> 0 | E109: =AVERAGE(E12:E31) -> 0 | F109: =AVERAGE(F12:F31) -> 0 | G109: =AVERAGE(G12:G31) -> 0 | H109: =AVERAGE(H12:H31) -> 0 | I109: =AVERAGE(I12:I31) -> 0 | K109: =AVERAGE(K12:K31) -> #DIV/0! | L109: =AVERAGE(L12:L31) -> #DIV/0! | M109: =AVERAGE(M12:M31) -> #DIV/0! | N109: =AVERAGE(N12:N31) -> #DIV/0! | O109: =AVERAGE(O12:O31) -> #DIV/0! | P109: =AVERAGE(P12:P31) -> #DIV/0! | R109: =AVERAGE(R12:R31) -> #DIV/0! | S109: =AVERAGE(S12:S31) -> #DIV/0! | T109: =AVERAGE(T12:T31) -> #DIV/0! | U109: =AVERAGE(U12:U31) -> #DIV/0! | V109: =AVERAGE(V12:V31) -> #DIV/0! | W109: =AVERAGE(W12:W31) -> #DIV/0! | Y109: =AVERAGE(Y12:Y31) -> #DIV/0! | Z109: =AVERAGE(Z12:Z31) -> #DIV/0! | AA109: =AVERAGE(AA12:AA31) -> #DIV/0! | AB109: =AVERAGE(AB12:AB31) -> #DIV/0! | AC109: =AVERAGE(AC12:AC31) -> #DIV/0! | AD109: =AVERAGE(AD12:AD31) -> #DIV/0! | AE109: =AVERAGE(AE12:AE31) -> #DIV/0!
A110: 1998-2002 | B110: =AVERAGE(B32:B51) -> 190436.36 | D110: =AVERAGE(D32:D51) -> 0 | E110: =AVERAGE(E32:E51) -> 0 | F110: =AVERAGE(F32:F51) -> 0 | G110: =AVERAGE(G32:G51) -> 0 | H110: =AVERAGE(H32:H51) -> 0 | I110: =AVERAGE(I32:I51) -> 0 | K110: =AVERAGE(K32:K51) -> 0 | L110: =AVERAGE(L32:L51) -> 0 | M110: =AVERAGE(M32:M51) -> 0 | N110: =AVERAGE(N32:N51) -> 0 | O110: =AVERAGE(O32:O51) -> 0 | P110: =AVERAGE(P32:P51) -> 0 | R110: =AVERAGE(R32:R51) -> #DIV/0! | S110: =AVERAGE(S32:S51) -> #DIV/0! | T110: =AVERAGE(T32:T51) -> #DIV/0! | U110: =AVERAGE(U32:U51) -> #DIV/0! | V110: =AVERAGE(V32:V51) -> #DIV/0! | W110: =AVERAGE(W32:W51) -> #DIV/0! | Y110: =AVERAGE(Y32:Y51) -> #DIV/0! | Z110: =AVERAGE(Z32:Z51) -> #DIV/0! | AA110: =AVERAGE(AA32:AA51) -> #DIV/0! | AB110: =AVERAGE(AB32:AB51) -> #DIV/0! | AC110: =AVERAGE(AC32:AC51) -> #DIV/0! | AD110: =AVERAGE(AD32:AD51) -> #DIV/0! | AE110: =AVERAGE(AE32:AE51) -> #DIV/0!
A111: 2003-2007 | B111: =AVERAGE(B52:B71) -> 246801.32 | D111: =AVERAGE(D52:D71) -> 0 | E111: =AVERAGE(E52:E71) -> 0 | F111: =AVERAGE(F52:F71) -> 0 | G111: =AVERAGE(G52:G71) -> 0 | H111: =AVERAGE(H52:H71) -> 0 | I111: =AVERAGE(I52:I71) -> 0 | K111: =AVERAGE(K52:K71) -> 0 | L111: =AVERAGE(L52:L71) -> 0 | M111: =AVERAGE(M52:M71) -> 0 | N111: =AVERAGE(N52:N71) -> 0 | O111: =AVERAGE(O52:O71) -> 0 | P111: =AVERAGE(P52:P71) -> 0 | R111: =AVERAGE(R52:R71) -> #DIV/0! | S111: =AVERAGE(S52:S71) -> #DIV/0! | T111: =AVERAGE(T52:T71) -> #DIV/0! | U111: =AVERAGE(U52:U71) -> #DIV/0! | V111: =AVERAGE(V52:V71) -> #DIV/0! | W111: =AVERAGE(W52:W71) -> #DIV/0! | Y111: =AVERAGE(Y52:Y71) -> 7.3666633 | Z111: =AVERAGE(Z52:Z71) -> 0 | AA111: =AVERAGE(AA52:AA71) -> 0 | AB111: =AVERAGE(AB52:AB71) -> 0 | AC111: =AVERAGE(AC52:AC71) -> 0 | AD111: =AVERAGE(AD52:AD71) -> 0 | AE111: =AVERAGE(AE52:AE71) -> 0
A112: 2008-2012 | B112: =AVERAGE(B72:B91) -> 301314.16 | D112: =AVERAGE(D72:D91) -> 302782.92 | E112: =AVERAGE(E72:E91) -> 12860.665 | F112: =AVERAGE(F72:F91) -> 16643.33 | G112: =AVERAGE(G72:G91) -> 51475.515 | H112: =AVERAGE(H72:H91) -> 68564.62 | I112: =AVERAGE(I72:I91) -> 153238.79 | K112: =AVERAGE(K72:K91) -> 98.416752 | L112: =AVERAGE(L72:L91) -> 4.1683167 | M112: =AVERAGE(M72:M91) -> 5.4042708 | N112: =AVERAGE(N72:N91) -> 16.795144 | O112: =AVERAGE(O72:O91) -> 22.409987 | P112: =AVERAGE(P72:P91) -> 49.639033 | R112: =AVERAGE(R72:R91) -> #DIV/0! | S112: =AVERAGE(S72:S91) -> #DIV/0! | T112: =AVERAGE(T72:T91) -> #DIV/0! | U112: =AVERAGE(U72:U91) -> #DIV/0! | V112: =AVERAGE(V72:V91) -> #DIV/0! | W112: =AVERAGE(W72:W91) -> #DIV/0! | Y112: =AVERAGE(Y72:Y91) -> 4.0875894 | Z112: =AVERAGE(Z72:Z91) -> 31.010288 | AA112: =AVERAGE(AA72:AA91) -> 1.3155767 | AB112: =AVERAGE(AB72:AB91) -> 1.7014422 | AC112: =AVERAGE(AC72:AC91) -> 4.9887293 | AD112: =AVERAGE(AD72:AD91) -> 6.6455116 | AE112: =AVERAGE(AE72:AE91) -> 16.359028
A113: 2013-2016 | B113: =AVERAGE(B92:B106) -> 394750.36 | D113: =AVERAGE(D92:D106) -> 543003.71 | E113: =AVERAGE(E92:E106) -> 25121.32 | F113: =AVERAGE(F92:F106) -> 25460.86 | G113: =AVERAGE(G92:G106) -> 75055.98 | H113: =AVERAGE(H92:H106) -> 109217.22 | I113: =AVERAGE(I92:I106) -> 308148.33 | K113: =AVERAGE(K92:K106) -> 137.31506 | L113: =AVERAGE(L92:L106) -> 6.3600464 | M113: =AVERAGE(M92:M106) -> 6.4574864 | N113: =AVERAGE(N92:N106) -> 19.011789 | O113: =AVERAGE(O92:O106) -> 27.688039 | P113: =AVERAGE(P92:P106) -> 77.797703 | R113: =AVERAGE(R92:R106) -> 8.4994406 | S113: =AVERAGE(S92:S106) -> 10.38466 | T113: =AVERAGE(T92:T106) -> 3.2072692 | U113: =AVERAGE(U92:U106) -> 3.1950204 | V113: =AVERAGE(V92:V106) -> 5.1298574 | W113: =AVERAGE(W92:W106) -> 11.610754 | Y113: =AVERAGE(Y92:Y106) -> 5.8200542 | Z113: =AVERAGE(Z92:Z106) -> 11.299725 | AA113: =AVERAGE(AA92:AA106) -> 0.58367808 | AB113: =AVERAGE(AB92:AB106) -> 0.1996762 | AC113: =AVERAGE(AC92:AC106) -> 0.6067625 | AD113: =AVERAGE(AD92:AD106) -> 1.4242987 | AE113: =AVERAGE(AE92:AE106) -> 8.4853092

Sheet 2a. Özel Tük. Grafikler
B1: Ülke Analizi
B2: Toplam Talep Analizi
B3: Özel Tüketim Analizi

Sheet 3. Özel Yatırımlar
B1: Ülke Analizi
B2: Toplam Talep Analizi
B3: Özel Yatırım ve Sermaye Stoku Analizi
I8: =E11/$B11*100 | R8: =((D15-D11)/$B11)*100 | S8: =((E15-E11)/$B11)*100 | T8: =((F15-F11)/$B11)*100
D9: Özel Reel Brüt Sabit Sermaye Oluşumu Bileşenleri (GFCFp) (Düzey, 2008 Fiyatları-DND Milyar) | H9: Özel Yatırım Bileşenlerinin Reel GSYH içindeki Payı | L9: Özel Yatırım Bileşenlerinin Reel GSYH içindeki Payının Büyüme Oranları (Year over Year) | Q9: Özel Yatırımların GSYH Büyümesine Katkısı (Year over Year)
A10: Year | B10: Reel GSYH (Düzey, 2008 Fiyatları-DND Milyar) | D10: Toplam GFCFp | E10: Özel Makina & Ekipman | F10: Özel İnşaat | H10: Toplam GFCFp | I10: Makina & Ekipman | J10: İnşaat | L10: Reel GSYH Büyüme | M10: Toplam GFCFp | N10: Makina & Ekipman | O10: İnşaat | Q10: Reel GSYH | R10: Toplam GFCFp | S10: Makina & Ekipman | T10: İnşaat
A11: Q1-1993 | B11: ='1.Reel GSYH '!B9 -> 0 | D11: ='1.Reel GSYH '!Q9 -> 0 | E11: ='1.Reel GSYH '!R9 -> 0 | F11: ='1.Reel GSYH '!S9 -> 0 | H11: =D11/$B11*100 -> #DIV/0! | I11: =E11/$B11*100 -> #DIV/0! | J11: =F11/$B11*100 -> #DIV/0!
A12: Q2-1993 | B12: ='1.Reel GSYH '!B10 -> 0 | D12: ='1.Reel GSYH '!Q10 -> 0 | E12: ='1.Reel GSYH '!R10 -> 0 | F12: ='1.Reel GSYH '!S10 -> 0 | H12: =D12/$B12*100 -> #DIV/0! | I12: =E12/$B12*100 -> #DIV/0! | J12: =F12/$B12*100 -> #DIV/0!
A13: Q3-1993 | B13: ='1.Reel GSYH '!B11 -> 0 | D13: ='1.Reel GSYH '!Q11 -> 0 | E13: ='1.Reel GSYH '!R11 -> 0 | F13: ='1.Reel GSYH '!S11 -> 0 | H13: =D13/$B13*100 -> #DIV/0! | I13: =E13/$B13*100 -> #DIV/0! | J13: =F13/$B13*100 -> #DIV/0!
A14: Q4-1993 | B14: ='1.Reel GSYH '!B12 -> 0 | D14: ='1.Reel GSYH '!Q12 -> 0 | E14: ='1.Reel GSYH '!R12 -> 0 | F14: ='1.Reel GSYH '!S12 -> 0 | H14: =D14/$B14*100 -> #DIV/0! | I14: =E14/$B14*100 -> #DIV/0! | J14: =F14/$B14*100 -> #DIV/0!
A15: Q1-1994 | B15: ='1.Reel GSYH '!B13 -> 0 | D15: ='1.Reel GSYH '!Q13 -> 0 | E15: ='1.Reel GSYH '!R13 -> 0 | F15: ='1.Reel GSYH '!S13 -> 0 | H15: =D15/$B15*100 -> #DIV/0! | I15: =E15/$B15*100 -> #DIV/0! | J15: =F15/$B15*100 -> #DIV/0! | L15: =(B15/B11-1)*100 -> #DIV/0! | M15: =(D15/D11-1)*100 -> #DIV/0! | N15: =(E15/E11-1)*100 -> #DIV/0! | O15: =(F15/F11-1)*100 -> #DIV/0! | Q15: =(B15/B11-1)*100 -> #DIV/0! | R15: =((D15-D11)/$B11)*100 -> #DIV/0! | S15: =((E15-E11)/$B11)*100 -> #DIV/0! | T15: =((F15-F11)/$B11)*100 -> #DIV/0!
A16: Q2-1994 | B16: ='1.Reel GSYH '!B14 -> 0 | D16: ='1.Reel GSYH '!Q14 -> 0 | E16: ='1.Reel GSYH '!R14 -> 0 | F16: ='1.Reel GSYH '!S14 -> 0 | H16: =D16/$B16*100 -> #DIV/0! | I16: =E16/$B16*100 -> #DIV/0! | J16: =F16/$B16*100 -> #DIV/0! | L16: =(B16/B12-1)*100 -> #DIV/0! | M16: =(D16/D12-1)*100 -> #DIV/0! | N16: =(E16/E12-1)*100 -> #DIV/0! | O16: =(F16/F12-1)*100 -> #DIV/0! | Q16: =(B16/B12-1)*100 -> #DIV/0! | R16: =((D16-D12)/$B12)*100 -> #DIV/0! | S16: =((E16-E12)/$B12)*100 -> #DIV/0! | T16: =((F16-F12)/$B12)*100 -> #DIV/0!
A17: Q3-1994 | B17: ='1.Reel GSYH '!B15 -> 0 | D17: ='1.Reel GSYH '!Q15 -> 0 | E17: ='1.Reel GSYH '!R15 -> 0 | F17: ='1.Reel GSYH '!S15 -> 0 | H17: =D17/$B17*100 -> #DIV/0! | I17: =E17/$B17*100 -> #DIV/0! | J17: =F17/$B17*100 -> #DIV/0! | L17: =(B17/B13-1)*100 -> #DIV/0! | M17: =(D17/D13-1)*100 -> #DIV/0! | N17: =(E17/E13-1)*100 -> #DIV/0! | O17: =(F17/F13-1)*100 -> #DIV/0! | Q17: =(B17/B13-1)*100 -> #DIV/0! | R17: =((D17-D13)/$B13)*100 -> #DIV/0! | S17: =((E17-E13)/$B13)*100 -> #DIV/0! | T17: =((F17-F13)/$B13)*100 -> #DIV/0!
A18: Q4-1994 | B18: ='1.Reel GSYH '!B16 -> 0 | D18: ='1.Reel GSYH '!Q16 -> 0 | E18: ='1.Reel GSYH '!R16 -> 0 | F18: ='1.Reel GSYH '!S16 -> 0 | H18: =D18/$B18*100 -> #DIV/0! | I18: =E18/$B18*100 -> #DIV/0! | J18: =F18/$B18*100 -> #DIV/0! | L18: =(B18/B14-1)*100 -> #DIV/0! | M18: =(D18/D14-1)*100 -> #DIV/0! | N18: =(E18/E14-1)*100 -> #DIV/0! | O18: =(F18/F14-1)*100 -> #DIV/0! | Q18: =(B18/B14-1)*100 -> #DIV/0! | R18: =((D18-D14)/$B14)*100 -> #DIV/0! | S18: =((E18-E14)/$B14)*100 -> #DIV/0! | T18: =((F18-F14)/$B14)*100 -> #DIV/0!
A19: Q1-1995 | B19: ='1.Reel GSYH '!B17 -> 0 | D19: ='1.Reel GSYH '!Q17 -> 0 | E19: ='1.Reel GSYH '!R17 -> 0 | F19: ='1.Reel GSYH '!S17 -> 0 | H19: =D19/$B19*100 -> #DIV/0! | I19: =E19/$B19*100 -> #DIV/0! | J19: =F19/$B19*100 -> #DIV/0! | L19: =(B19/B15-1)*100 -> #DIV/0! | M19: =(D19/D15-1)*100 -> #DIV/0! | N19: =(E19/E15-1)*100 -> #DIV/0! | O19: =(F19/F15-1)*100 -> #DIV/0! | Q19: =(B19/B15-1)*100 -> #DIV/0! | R19: =((D19-D15)/$B15)*100 -> #DIV/0! | S19: =((E19-E15)/$B15)*100 -> #DIV/0! | T19: =((F19-F15)/$B15)*100 -> #DIV/0!
A20: Q2-1995 | B20: ='1.Reel GSYH '!B18 -> 0 | D20: ='1.Reel GSYH '!Q18 -> 0 | E20: ='1.Reel GSYH '!R18 -> 0 | F20: ='1.Reel GSYH '!S18 -> 0 | H20: =D20/$B20*100 -> #DIV/0! | I20: =E20/$B20*100 -> #DIV/0! | J20: =F20/$B20*100 -> #DIV/0! | L20: =(B20/B16-1)*100 -> #DIV/0! | M20: =(D20/D16-1)*100 -> #DIV/0! | N20: =(E20/E16-1)*100 -> #DIV/0! | O20: =(F20/F16-1)*100 -> #DIV/0! | Q20: =(B20/B16-1)*100 -> #DIV/0! | R20: =((D20-D16)/$B16)*100 -> #DIV/0! | S20: =((E20-E16)/$B16)*100 -> #DIV/0! | T20: =((F20-F16)/$B16)*100 -> #DIV/0!
A21: Q3-1995 | B21: ='1.Reel GSYH '!B19 -> 0 | D21: ='1.Reel GSYH '!Q19 -> 0 | E21: ='1.Reel GSYH '!R19 -> 0 | F21: ='1.Reel GSYH '!S19 -> 0 | H21: =D21/$B21*100 -> #DIV/0! | I21: =E21/$B21*100 -> #DIV/0! | J21: =F21/$B21*100 -> #DIV/0! | L21: =(B21/B17-1)*100 -> #DIV/0! | M21: =(D21/D17-1)*100 -> #DIV/0! | N21: =(E21/E17-1)*100 -> #DIV/0! | O21: =(F21/F17-1)*100 -> #DIV/0! | Q21: =(B21/B17-1)*100 -> #DIV/0! | R21: =((D21-D17)/$B17)*100 -> #DIV/0! | S21: =((E21-E17)/$B17)*100 -> #DIV/0! | T21: =((F21-F17)/$B17)*100 -> #DIV/0!
A22: Q4-1995 | B22: ='1.Reel GSYH '!B20 -> 0 | D22: ='1.Reel GSYH '!Q20 -> 0 | E22: ='1.Reel GSYH '!R20 -> 0 | F22: ='1.Reel GSYH '!S20 -> 0 | H22: =D22/$B22*100 -> #DIV/0! | I22: =E22/$B22*100 -> #DIV/0! | J22: =F22/$B22*100 -> #DIV/0! | L22: =(B22/B18-1)*100 -> #DIV/0! | M22: =(D22/D18-1)*100 -> #DIV/0! | N22: =(E22/E18-1)*100 -> #DIV/0! | O22: =(F22/F18-1)*100 -> #DIV/0! | Q22: =(B22/B18-1)*100 -> #DIV/0! | R22: =((D22-D18)/$B18)*100 -> #DIV/0! | S22: =((E22-E18)/$B18)*100 -> #DIV/0! | T22: =((F22-F18)/$B18)*100 -> #DIV/0!
A23: Q1-1996 | B23: ='1.Reel GSYH '!B21 -> 0 | D23: ='1.Reel GSYH '!Q21 -> 0 | E23: ='1.Reel GSYH '!R21 -> 0 | F23: ='1.Reel GSYH '!S21 -> 0 | H23: =D23/$B23*100 -> #DIV/0! | I23: =E23/$B23*100 -> #DIV/0! | J23: =F23/$B23*100 -> #DIV/0! | L23: =(B23/B19-1)*100 -> #DIV/0! | M23: =(D23/D19-1)*100 -> #DIV/0! | N23: =(E23/E19-1)*100 -> #DIV/0! | O23: =(F23/F19-1)*100 -> #DIV/0! | Q23: =(B23/B19-1)*100 -> #DIV/0! | R23: =((D23-D19)/$B19)*100 -> #DIV/0! | S23: =((E23-E19)/$B19)*100 -> #DIV/0! | T23: =((F23-F19)/$B19)*100 -> #DIV/0!
A24: Q2-1996 | B24: ='1.Reel GSYH '!B22 -> 0 | D24: ='1.Reel GSYH '!Q22 -> 0 | E24: ='1.Reel GSYH '!R22 -> 0 | F24: ='1.Reel GSYH '!S22 -> 0 | H24: =D24/$B24*100 -> #DIV/0! | I24: =E24/$B24*100 -> #DIV/0! | J24: =F24/$B24*100 -> #DIV/0! | L24: =(B24/B20-1)*100 -> #DIV/0! | M24: =(D24/D20-1)*100 -> #DIV/0! | N24: =(E24/E20-1)*100 -> #DIV/0! | O24: =(F24/F20-1)*100 -> #DIV/0! | Q24: =(B24/B20-1)*100 -> #DIV/0! | R24: =((D24-D20)/$B20)*100 -> #DIV/0! | S24: =((E24-E20)/$B20)*100 -> #DIV/0! | T24: =((F24-F20)/$B20)*100 -> #DIV/0!
A25: Q3-1996 | B25: ='1.Reel GSYH '!B23 -> 0 | D25: ='1.Reel GSYH '!Q23 -> 0 | E25: ='1.Reel GSYH '!R23 -> 0 | F25: ='1.Reel GSYH '!S23 -> 0 | H25: =D25/$B25*100 -> #DIV/0! | I25: =E25/$B25*100 -> #DIV/0! | J25: =F25/$B25*100 -> #DIV/0! | L25: =(B25/B21-1)*100 -> #DIV/0! | M25: =(D25/D21-1)*100 -> #DIV/0! | N25: =(E25/E21-1)*100 -> #DIV/0! | O25: =(F25/F21-1)*100 -> #DIV/0! | Q25: =(B25/B21-1)*100 -> #DIV/0! | R25: =((D25-D21)/$B21)*100 -> #DIV/0! | S25: =((E25-E21)/$B21)*100 -> #DIV/0! | T25: =((F25-F21)/$B21)*100 -> #DIV/0!
A26: Q4-1996 | B26: ='1.Reel GSYH '!B24 -> 0 | D26: ='1.Reel GSYH '!Q24 -> 0 | E26: ='1.Reel GSYH '!R24 -> 0 | F26: ='1.Reel GSYH '!S24 -> 0 | H26: =D26/$B26*100 -> #DIV/0! | I26: =E26/$B26*100 -> #DIV/0! | J26: =F26/$B26*100 -> #DIV/0! | L26: =(B26/B22-1)*100 -> #DIV/0! | M26: =(D26/D22-1)*100 -> #DIV/0! | N26: =(E26/E22-1)*100 -> #DIV/0! | O26: =(F26/F22-1)*100 -> #DIV/0! | Q26: =(B26/B22-1)*100 -> #DIV/0! | R26: =((D26-D22)/$B22)*100 -> #DIV/0! | S26: =((E26-E22)/$B22)*100 -> #DIV/0! | T26: =((F26-F22)/$B22)*100 -> #DIV/0!
... A105: Q3-2016 | B105: ='1.Reel GSYH '!B103 -> 7.8800443e+10 | D105: ='1.Reel GSYH '!Q103 -> 0 | E105: ='1.Reel GSYH '!R103 -> 0 | F105: ='1.Reel GSYH '!S103 -> 0 | H105: =D105/$B105*100 -> 0 | I105: =E105/$B105*100 -> 0 | J105: =F105/$B105*100 -> 0 | L105: =(B105/B101-1)*100 -> 6.3735739 | M105: =(D105/D101-1)*100 -> #DIV/0! | N105: =(E105/E101-1)*100 -> #DIV/0! | O105: =(F105/F101-1)*100 -> #DIV/0! | Q105: =(B105/B101-1)*100 -> 6.3735739 | R105: =((D105-D101)/$B101)*100 -> 0 | S105: =((E105-E101)/$B101)*100 -> 0 | T105: =((F105-F101)/$B101)*100 -> 0
M106: Payların Büyüme Oranı | R106: Büyümeye Katkı
L107: Reel GSYH Büyüme | M107: Toplam GFCFp | N107: Makina & Ekipman | O107: İnşaat | Q107: Reel GSYH Büyüme | R107: Toplam GFCFp | S107: Makina & Ekipman | T107: İnşaat
A109: 1993-1997 | B109: =AVERAGE(B12:B31) -> 0 | D109: =AVERAGE(D12:D31) -> 0 | E109: =AVERAGE(E12:E31) -> 0 | F109: =AVERAGE(F12:F31) -> 0 | H109: =AVERAGE(H12:H31) -> #DIV/0! | I109: =AVERAGE(I12:I31) -> #DIV/0! | J109: =AVERAGE(J12:J31) -> #DIV/0! | K109: 1993-1997 | L109: =AVERAGE(L12:L31) -> #DIV/0! | M109: =AVERAGE(M12:M31) -> #DIV/0! | N109: =AVERAGE(N12:N31) -> #DIV/0! | O109: =AVERAGE(O12:O31) -> #DIV/0! | P109: 1993-1997 | Q109: =AVERAGE(Q12:Q31) -> #DIV/0! | R109: =AVERAGE(R12:R31) -> #DIV/0! | S109: =AVERAGE(S12:S31) -> #DIV/0! | T109: =AVERAGE(T12:T31) -> #DIV/0!
A110: 1998-2002 | B110: =AVERAGE(B32:B51) -> 0 | D110: =AVERAGE(D32:D51) -> 0 | E110: =AVERAGE(E32:E51) -> 0 | F110: =AVERAGE(F32:F51) -> 0 | H110: =AVERAGE(H32:H51) -> #DIV/0! | I110: =AVERAGE(I32:I51) -> #DIV/0! | J110: =AVERAGE(J32:J51) -> #DIV/0! | K110: 1998-2002 | L110: =AVERAGE(L32:L51) -> #DIV/0! | M110: =AVERAGE(M32:M51) -> #DIV/0! | N110: =AVERAGE(N32:N51) -> #DIV/0! | O110: =AVERAGE(O32:O51) -> #DIV/0! | P110: 1998-2002 | Q110: =AVERAGE(Q32:Q51) -> #DIV/0! | R110: =AVERAGE(R32:R51) -> #DIV/0! | S110: =AVERAGE(S32:S51) -> #DIV/0! | T110: =AVERAGE(T32:T51) -> #DIV/0!
A111: 2003-2007 | B111: =AVERAGE(B52:B71) -> 0 | D111: =AVERAGE(D52:D71) -> 0 | E111: =AVERAGE(E52:E71) -> 0 | F111: =AVERAGE(F52:F71) -> 0 | H111: =AVERAGE(H52:H71) -> #DIV/0! | I111: =AVERAGE(I52:I71) -> #DIV/0! | J111: =AVERAGE(J52:J71) -> #DIV/0! | K111: 2003-2007 | L111: =AVERAGE(L52:L71) -> #DIV/0! | M111: =AVERAGE(M52:M71) -> #DIV/0! | N111: =AVERAGE(N52:N71) -> #DIV/0! | O111: =AVERAGE(O52:O71) -> #DIV/0! | P111: 2003-2007 | Q111: =AVERAGE(Q52:Q71) -> #DIV/0! | R111: =AVERAGE(R52:R71) -> #DIV/0! | S111: =AVERAGE(S52:S71) -> #DIV/0! | T111: =AVERAGE(T52:T71) -> #DIV/0!
A112: 2008-2012 | B112: =AVERAGE(B72:B91) -> 2.835242e+10 | D112: =AVERAGE(D72:D91) -> 0 | E112: =AVERAGE(E72:E91) -> 0 | F112: =AVERAGE(F72:F91) -> 0 | H112: =AVERAGE(H72:H91) -> #DIV/0! | I112: =AVERAGE(I72:I91) -> #DIV/0! | J112: =AVERAGE(J72:J91) -> #DIV/0! | K112: 2008-2012 | L112: =AVERAGE(L72:L91) -> #DIV/0! | M112: =AVERAGE(M72:M91) -> #DIV/0! | N112: =AVERAGE(N72:N91) -> #DIV/0! | O112: =AVERAGE(O72:O91) -> #DIV/0! | P112: 2008-2012 | Q112: =AVERAGE(Q72:Q91) -> #DIV/0! | R112: =AVERAGE(R72:R91) -> #DIV/0! | S112: =AVERAGE(S72:S91) -> #DIV/0! | T112: =AVERAGE(T72:T91) -> #DIV/0!
A113: 2013-2016 | B113: =AVERAGE(B92:B106) -> 6.1674362e+10 | D113: =AVERAGE(D92:D106) -> 0 | E113: =AVERAGE(E92:E106) -> 0 | F113: =AVERAGE(F92:F106) -> 0 | H113: =AVERAGE(H92:H106) -> 0 | I113: =AVERAGE(I92:I106) -> 0 | J113: =AVERAGE(J92:J106) -> 0 | K113: 2013-2016 | L113: =AVERAGE(L92:L106) -> 21.027797 | M113: =AVERAGE(M92:M106) -> #DIV/0! | N113: =AVERAGE(N92:N106) -> #DIV/0! | O113: =AVERAGE(O92:O106) -> #DIV/0! | P113: 2013-2016 | Q113: =AVERAGE(Q92:Q106) -> 21.027797 | R113: =AVERAGE(R92:R106) -> 0 | S113: =AVERAGE(S92:S106) -> 0 | T113: =AVERAGE(T92:T106) -> 0

Sheet 3a. Özel Yatırım Grafikler
B1: Ülke Analizi
B2: Toplam Talep Analizi
B3: Özel Yatırım ve Sermaye Stoku Analizi

Sheet KAYNAKÇA
A1: Çalışmamda kullandığım veriler
A2: https://fred.stlouisfed.org/series/NGDPRSAXDCTRQ
A3: https://fred.stlouisfed.org/series/TURPFCEQDSMEI
A4: https://fred.stlouisfed.org/series/IGDXEDTRM086NEST
A5: https://fred.stlouisfed.org/series/NAEXKP02TRQ189S
A6: https://fred.stlouisfed.org/series/IGDXEDTRM086NEST
A7: https://fred.stlouisfed.org/series/TURPITGND02GPM
A8: https://fred.stlouisfed.org/series/TURGFCEQDSMEI
A9: https://fred.stlouisfed.org/series/TURGFCFQDSMEI
A10: https://tradingeconomics.com/turkey/gross-fixed-capital-formation
A11: https://fred.stlouisfed.org/series/TURIMPORTQDSMEI
A12: https://evds2.tcmb.gov.tr/index.php?/evds/serieMarket/collapse_15/5963/DataGroup/turkish/bie_cdur2/

Sheet 5. Summary
A5: Growth Determinants: Does each point to higher or lower growth in 2016?
B6: Sheet | D6: Higher Growth | E6: Lower Growth | F6: No change | G6: Meet 5% Target? | I6: Notes
A8: Aggregate Demand
A9: Private Consumption | B9: 2a
A10: Private Investment | B10: 3a
A11: Public Consumption | B11: 2a
A12: Public Investment | B12: 3a
A14: Business Cycle Indicators: Does each point to higher or lower growth in 2016?
A16: Real GDP Growth | B16: 4a
A17: Inflation | B17: 4a
A18: Industrial Production | B18: 4a
A19: Exports of Goods & Services | B19: 4a
A20: Imports of Goods & Services | B20: 4a
A21: Credit to the Private Sector | B21: 4a
A22: Unemployment | B22: 4a
A24: Risks
A26: Will the 5% growth target be met in 2016-17?
A27: What is your forecast for growth in 2016?
A28: (Enter your forecast in the Sheet 6)
